Workbook

Sheet Sheet1
A1: ColB | B1: DPST | C1: DpstName | D1: Item | E1: Item_desc | F1: ProductGroups | G1: New PG | H1: NewProductGrp
A2: =B2&D2 -> 90041120326630 | B2: 90041 | C2: AED - SPARES | D2: 120326630 | E2: LOCK ASSY RIGHT | F2: SPARES / ACCESSORIES | H2: =IF(LEN(G2)<2,F2,G2) -> SPARES / ACCESSORIES | I2: ="update ats_prd_master_new set ProductGroups= "&"'"&H2&"'"&"where ProductGroups="&"'"&F2&"'"&" and DPST= "&"'"&B2&"'"&"and item= "&"'"&D2&"'" -> update ats_prd_master_new set ProductGroups= 'SPARES / ACCESSORIES'where ProductGroups='SPARES / ACCESSORIES' and DPST= '90041'and item= '120326630'
A3: =B3&D3 -> 90041120353370 | B3: 90041 | C3: AED - SPARES | D3: 120353370 | E3: COVER;TOP;MOTOR | F3: SPARES / ACCESSORIES | H3: =IF(LEN(G3)<2,F3,G3) -> SPARES / ACCESSORIES | I3: ="update ats_prd_master_new set ProductGroups= "&"'"&H3&"'"&"where ProductGroups="&"'"&F3&"'"&" and DPST= "&"'"&B3&"'"&"and item= "&"'"&D3&"'" -> update ats_prd_master_new set ProductGroups= 'SPARES / ACCESSORIES'where ProductGroups='SPARES / ACCESSORIES' and DPST= '90041'and item= '120353370'
A4: =B4&D4 -> 90041120355460 | B4: 90041 | C4: AED - SPARES | D4: 120355460 | E4: TOP PLATE ASSY FOLL POWDER COA | F4: SPARES / ACCESSORIES | H4: =IF(LEN(G4)<2,F4,G4) -> SPARES / ACCESSORIES | I4: ="update ats_prd_master_new set ProductGroups= "&"'"&H4&"'"&"where ProductGroups="&"'"&F4&"'"&" and DPST= "&"'"&B4&"'"&"and item= "&"'"&D4&"'" -> update ats_prd_master_new set ProductGroups= 'SPARES / ACCESSORIES'where ProductGroups='SPARES / ACCESSORIES' and DPST= '90041'and item= '120355460'
A5: =B5&D5 -> 900411203SA1000NU | B5: 90041 | C5: AED - SPARES | D5: 1203SA1000NU | E5: PIN SA1000-WSC | F5: SPARES / ACCESSORIES | H5: =IF(LEN(G5)<2,F5,G5) -> SPARES / ACCESSORIES | I5: ="update ats_prd_master_new set ProductGroups= "&"'"&H5&"'"&"where ProductGroups="&"'"&F5&"'"&" and DPST= "&"'"&B5&"'"&"and item= "&"'"&D5&"'" -> update ats_prd_master_new set ProductGroups= 'SPARES / ACCESSORIES'where ProductGroups='SPARES / ACCESSORIES' and DPST= '90041'and item= '1203SA1000NU'
A6: =B6&D6 -> 90041120418960 | B6: 90041 | C6: AED - SPARES | D6: 120418960 | E6: HOSE ASSY (3 MTRS) | F6: SPARES / ACCESSORIES | H6: =IF(LEN(G6)<2,F6,G6) -> SPARES / ACCESSORIES | I6: ="update ats_prd_master_new set ProductGroups= "&"'"&H6&"'"&"where ProductGroups="&"'"&F6&"'"&" and DPST= "&"'"&B6&"'"&"and item= "&"'"&D6&"'" -> update ats_prd_master_new set ProductGroups= 'SPARES / ACCESSORIES'where ProductGroups='SPARES / ACCESSORIES' and DPST= '90041'and item= '120418960'
A7: =B7&D7 -> 90041120430551 | B7: 90041 | C7: AED - SPARES | D7: 120430551 | E7: UNION TEE DIA6MM | F7: SPARES / ACCESSORIES | H7: =IF(LEN(G7)<2,F7,G7) -> SPARES / ACCESSORIES | I7: ="update ats_prd_master_new set ProductGroups= "&"'"&H7&"'"&"where ProductGroups="&"'"&F7&"'"&" and DPST= "&"'"&B7&"'"&"and item= "&"'"&D7&"'" -> update ats_prd_master_new set ProductGroups= 'SPARES / ACCESSORIES'where ProductGroups='SPARES / ACCESSORIES' and DPST= '90041'and item= '120430551'
A8: =B8&D8 -> 90041120430552 | B8: 90041 | C8: AED - SPARES | D8: 120430552 | E8: MALE CONNECTOR DIA6X5MM | F8: SPARES / ACCESSORIES | H8: =IF(LEN(G8)<2,F8,G8) -> SPARES / ACCESSORIES | I8: ="update ats_prd_master_new set ProductGroups= "&"'"&H8&"'"&"where ProductGroups="&"'"&F8&"'"&" and DPST= "&"'"&B8&"'"&"and item= "&"'"&D8&"'" -> update ats_prd_master_new set ProductGroups= 'SPARES / ACCESSORIES'where ProductGroups='SPARES / ACCESSORIES' and DPST= '90041'and item= '120430552'
A9: =B9&D9 -> 90041120452510 | B9: 90041 | C9: AED - SPARES | D9: 120452510 | E9: COVER HOLDER; PIN - 3TON | F9: SPARES / ACCESSORIES | H9: =IF(LEN(G9)<2,F9,G9) -> SPARES / ACCESSORIES | I9: ="update ats_prd_master_new set ProductGroups= "&"'"&H9&"'"&"where ProductGroups="&"'"&F9&"'"&" and DPST= "&"'"&B9&"'"&"and item= "&"'"&D9&"'" -> update ats_prd_master_new set ProductGroups= 'SPARES / ACCESSORIES'where ProductGroups='SPARES / ACCESSORIES' and DPST= '90041'and item= '120452510'
A10: =B10&D10 -> 90041120453550 | B10: 90041 | C10: AED - SPARES | D10: 120453550 | E10: PULLEY MOTOR M/C SAL | F10: SPARES / ACCESSORIES | H10: =IF(LEN(G10)<2,F10,G10) -> SPARES / ACCESSORIES | I10: ="update ats_prd_master_new set ProductGroups= "&"'"&H10&"'"&"where ProductGroups="&"'"&F10&"'"&" and DPST= "&"'"&B10&"'"&"and item= "&"'"&D10&"'" -> update ats_prd_master_new set ProductGroups= 'SPARES / ACCESSORIES'where ProductGroups='SPARES / ACCESSORIES' and DPST= '90041'and item= '120453550'
A11: =B11&D11 -> 90041120454600 | B11: 90041 | C11: AED - SPARES | D11: 120454600 | E11: STUD ASSY,ARM - SAL HYN | F11: SPARES / ACCESSORIES | H11: =IF(LEN(G11)<2,F11,G11) -> SPARES / ACCESSORIES | I11: ="update ats_prd_master_new set ProductGroups= "&"'"&H11&"'"&"where ProductGroups="&"'"&F11&"'"&" and DPST= "&"'"&B11&"'"&"and item= "&"'"&D11&"'" -> update ats_prd_master_new set ProductGroups= 'SPARES / ACCESSORIES'where ProductGroups='SPARES / ACCESSORIES' and DPST= '90041'and item= '120454600'
A12: =B12&D12 -> 90041120463570 | B12: 90041 | C12: AED - SPARES | D12: 120463570 | E12: PIN (CYLINDER BOTTOM) | F12: SPARES / ACCESSORIES | H12: =IF(LEN(G12)<2,F12,G12) -> SPARES / ACCESSORIES | I12: ="update ats_prd_master_new set ProductGroups= "&"'"&H12&"'"&"where ProductGroups="&"'"&F12&"'"&" and DPST= "&"'"&B12&"'"&"and item= "&"'"&D12&"'" -> update ats_prd_master_new set ProductGroups= 'SPARES / ACCESSORIES'where ProductGroups='SPARES / ACCESSORIES' and DPST= '90041'and item= '120463570'
A13: =B13&D13 -> 90041120463850 | B13: 90041 | C13: AED - SPARES | D13: 120463850 | E13: BREATHER | F13: SPARES / ACCESSORIES | H13: =IF(LEN(G13)<2,F13,G13) -> SPARES / ACCESSORIES | I13: ="update ats_prd_master_new set ProductGroups= "&"'"&H13&"'"&"where ProductGroups="&"'"&F13&"'"&" and DPST= "&"'"&B13&"'"&"and item= "&"'"&D13&"'" -> update ats_prd_master_new set ProductGroups= 'SPARES / ACCESSORIES'where ProductGroups='SPARES / ACCESSORIES' and DPST= '90041'and item= '120463850'
... A23: =B23&D23 -> 90029SCIN0005 | B23: 90029 | C23: Rocd-service revenue | D23: SCIN0005 | E23: AMC CHARGES | F23: SERVICE BILLING | H23: =IF(LEN(G23)<2,F23,G23) -> SERVICE BILLING | I23: ="update ats_prd_master_new set ProductGroups= "&"'"&H23&"'"&"where ProductGroups="&"'"&F23&"'"&" and DPST= "&"'"&B23&"'"&"and item= "&"'"&D23&"'" -> update ats_prd_master_new set ProductGroups= 'SERVICE BILLING'where ProductGroups='SERVICE BILLING' and DPST= '90029'and item= 'SCIN0005'
A24: =B24&D24 -> 90029SCIN0006 | B24: 90029 | C24: Rocd-service revenue | D24: SCIN0006 | F24: SERVICE BILLING | H24: =IF(LEN(G24)<2,F24,G24) -> SERVICE BILLING | I24: ="update ats_prd_master_new set ProductGroups= "&"'"&H24&"'"&"where ProductGroups="&"'"&F24&"'"&" and DPST= "&"'"&B24&"'"&"and item= "&"'"&D24&"'" -> update ats_prd_master_new set ProductGroups= 'SERVICE BILLING'where ProductGroups='SERVICE BILLING' and DPST= '90029'and item= 'SCIN0006'
A25: =B25&D25 -> 90029SCIN0007 | B25: 90029 | C25: Rocd-service revenue | D25: SCIN0007 | F25: SERVICE BILLING | H25: =IF(LEN(G25)<2,F25,G25) -> SERVICE BILLING | I25: ="update ats_prd_master_new set ProductGroups= "&"'"&H25&"'"&"where ProductGroups="&"'"&F25&"'"&" and DPST= "&"'"&B25&"'"&"and item= "&"'"&D25&"'" -> update ats_prd_master_new set ProductGroups= 'SERVICE BILLING'where ProductGroups='SERVICE BILLING' and DPST= '90029'and item= 'SCIN0007'
A26: =B26&D26 -> 90029SCIN0008 | B26: 90029 | C26: Rocd-service revenue | D26: SCIN0008 | F26: SERVICE BILLING | H26: =IF(LEN(G26)<2,F26,G26) -> SERVICE BILLING | I26: ="update ats_prd_master_new set ProductGroups= "&"'"&H26&"'"&"where ProductGroups="&"'"&F26&"'"&" and DPST= "&"'"&B26&"'"&"and item= "&"'"&D26&"'" -> update ats_prd_master_new set ProductGroups= 'SERVICE BILLING'where ProductGroups='SERVICE BILLING' and DPST= '90029'and item= 'SCIN0008'
A27: =B27&D27 -> 90029SCIN0009 | B27: 90029 | C27: Rocd-service revenue | D27: SCIN0009 | F27: SERVICE BILLING | H27: =IF(LEN(G27)<2,F27,G27) -> SERVICE BILLING | I27: ="update ats_prd_master_new set ProductGroups= "&"'"&H27&"'"&"where ProductGroups="&"'"&F27&"'"&" and DPST= "&"'"&B27&"'"&"and item= "&"'"&D27&"'" -> update ats_prd_master_new set ProductGroups= 'SERVICE BILLING'where ProductGroups='SERVICE BILLING' and DPST= '90029'and item= 'SCIN0009'
A28: =B28&D28 -> 90040008400130 | B28: 90040 | C28: AED - MANUFACTURED UNITS | D28: 008400130 | E28: ON DELAY TIMER | F28: SPARES / ACCESSORIES | H28: =IF(LEN(G28)<2,F28,G28) -> SPARES / ACCESSORIES | I28: ="update ats_prd_master_new set ProductGroups= "&"'"&H28&"'"&"where ProductGroups="&"'"&F28&"'"&" and DPST= "&"'"&B28&"'"&"and item= "&"'"&D28&"'" -> update ats_prd_master_new set ProductGroups= 'SPARES / ACCESSORIES'where ProductGroups='SPARES / ACCESSORIES' and DPST= '90040'and item= '008400130'
A29: =B29&D29 -> 90040008937011 | B29: 90040 | C29: AED - MANUFACTURED UNITS | D29: 008937011 | E29: TRANSFORMER 50VA 415V-0-24V. | F29: SPARES / ACCESSORIES | H29: =IF(LEN(G29)<2,F29,G29) -> SPARES / ACCESSORIES | I29: ="update ats_prd_master_new set ProductGroups= "&"'"&H29&"'"&"where ProductGroups="&"'"&F29&"'"&" and DPST= "&"'"&B29&"'"&"and item= "&"'"&D29&"'" -> update ats_prd_master_new set ProductGroups= 'SPARES / ACCESSORIES'where ProductGroups='SPARES / ACCESSORIES' and DPST= '90040'and item= '008937011'
A30: =B30&D30 -> 90040080302630 | B30: 90040 | C30: AED - MANUFACTURED UNITS | D30: 080302630 | E30: CUSHION CHAIR | F30: MOBILE SERVICE UNITS | H30: =IF(LEN(G30)<2,F30,G30) -> MOBILE SERVICE UNITS | I30: ="update ats_prd_master_new set ProductGroups= "&"'"&H30&"'"&"where ProductGroups="&"'"&F30&"'"&" and DPST= "&"'"&B30&"'"&"and item= "&"'"&D30&"'" -> update ats_prd_master_new set ProductGroups= 'MOBILE SERVICE UNITS'where ProductGroups='MOBILE SERVICE UNITS' and DPST= '90040'and item= '080302630'
A31: =B31&D31 -> 90040080302730 | B31: 90040 | C31: AED - MANUFACTURED UNITS | D31: 080302730 | E31: AIR TANK ASSY | F31: MOBILE SERVICE UNITS | H31: =IF(LEN(G31)<2,F31,G31) -> MOBILE SERVICE UNITS | I31: ="update ats_prd_master_new set ProductGroups= "&"'"&H31&"'"&"where ProductGroups="&"'"&F31&"'"&" and DPST= "&"'"&B31&"'"&"and item= "&"'"&D31&"'" -> update ats_prd_master_new set ProductGroups= 'MOBILE SERVICE UNITS'where ProductGroups='MOBILE SERVICE UNITS' and DPST= '90040'and item= '080302730'
A32: =B32&D32 -> 90041130315300 | B32: 90041 | C32: AED - SPARES | D32: 130315300 | E32: COVER ASSY GREASE DRUM | F32: SPARES / ACCESSORIES | H32: =IF(LEN(G32)<2,F32,G32) -> SPARES / ACCESSORIES | I32: ="update ats_prd_master_new set ProductGroups= "&"'"&H32&"'"&"where ProductGroups="&"'"&F32&"'"&" and DPST= "&"'"&B32&"'"&"and item= "&"'"&D32&"'" -> update ats_prd_master_new set ProductGroups= 'SPARES / ACCESSORIES'where ProductGroups='SPARES / ACCESSORIES' and DPST= '90041'and item= '130315300'
A33: =B33&D33 -> 90041130416931 | B33: 90041 | C33: AED - SPARES | D33: 130416931 | E33: DRUM ASSY GREASE | F33: SPARES / ACCESSORIES | H33: =IF(LEN(G33)<2,F33,G33) -> SPARES / ACCESSORIES | I33: ="update ats_prd_master_new set ProductGroups= "&"'"&H33&"'"&"where ProductGroups="&"'"&F33&"'"&" and DPST= "&"'"&B33&"'"&"and item= "&"'"&D33&"'" -> update ats_prd_master_new set ProductGroups= 'SPARES / ACCESSORIES'where ProductGroups='SPARES / ACCESSORIES' and DPST= '90041'and item= '130416931'
A34: =B34&D34 -> 90040080302750 | B34: 90040 | C34: AED - MANUFACTURED UNITS | D34: 080302750 | E34: COMPRESSOR ASSY | F34: MMS | H34: =IF(LEN(G34)<2,F34,G34) -> MMS | I34: ="update ats_prd_master_new set ProductGroups= "&"'"&H34&"'"&"where ProductGroups="&"'"&F34&"'"&" and DPST= "&"'"&B34&"'"&"and item= "&"'"&D34&"'" -> update ats_prd_master_new set ProductGroups= 'MMS'where ProductGroups='MMS' and DPST= '90040'and item= '080302750'
A35: =B35&D35 -> 90041130453220 | B35: 90041 | C35: AED - SPARES | D35: 130453220 | E35: ADAPTER BUNG M/C | F35: SPARES / ACCESSORIES | H35: =IF(LEN(G35)<2,F35,G35) -> SPARES / ACCESSORIES | I35: ="update ats_prd_master_new set ProductGroups= "&"'"&H35&"'"&"where ProductGroups="&"'"&F35&"'"&" and DPST= "&"'"&B35&"'"&"and item= "&"'"&D35&"'" -> update ats_prd_master_new set ProductGroups= 'SPARES / ACCESSORIES'where ProductGroups='SPARES / ACCESSORIES' and DPST= '90041'and item= '130453220'
A36: =B36&D36 -> 90041130493020 | B36: 90041 | C36: AED - SPARES | D36: 130493020 | E36: PUMP WITH GUN ASSY-5 KG | F36: SPARES / ACCESSORIES | H36: =IF(LEN(G36)<2,F36,G36) -> SPARES / ACCESSORIES | I36: ="update ats_prd_master_new set ProductGroups= "&"'"&H36&"'"&"where ProductGroups="&"'"&F36&"'"&" and DPST= "&"'"&B36&"'"&"and item= "&"'"&D36&"'" -> update ats_prd_master_new set ProductGroups= 'SPARES / ACCESSORIES'where ProductGroups='SPARES / ACCESSORIES' and DPST= '90041'and item= '130493020'
A37: =B37&D37 -> 90040080302820 | B37: 90040 | C37: AED - MANUFACTURED UNITS | D37: 080302820 | E37: WATER TANK ASSY | F37: MMS | H37: =IF(LEN(G37)<2,F37,G37) -> MMS | I37: ="update ats_prd_master_new set ProductGroups= "&"'"&H37&"'"&"where ProductGroups="&"'"&F37&"'"&" and DPST= "&"'"&B37&"'"&"and item= "&"'"&D37&"'" -> update ats_prd_master_new set ProductGroups= 'MMS'where ProductGroups='MMS' and DPST= '90040'and item= '080302820'
A38: =B38&D38 -> 900411332HC0801PI | B38: 90041 | C38: AED - SPARES | D38: 1332HC0801PI | E38: WIND NOZZLE | F38: SPARES / ACCESSORIES | H38: =IF(LEN(G38)<2,F38,G38) -> SPARES / ACCESSORIES | I38: ="update ats_prd_master_new set ProductGroups= "&"'"&H38&"'"&"where ProductGroups="&"'"&F38&"'"&" and DPST= "&"'"&B38&"'"&"and item= "&"'"&D38&"'" -> update ats_prd_master_new set ProductGroups= 'SPARES / ACCESSORIES'where ProductGroups='SPARES / ACCESSORIES' and DPST= '90041'and item= '1332HC0801PI'
A39: =B39&D39 -> 900411332HC0803PI | B39: 90041 | C39: AED - SPARES | D39: 1332HC0803PI | E39: MINI BALL VALVE | F39: SPARES / ACCESSORIES | H39: =IF(LEN(G39)<2,F39,G39) -> SPARES / ACCESSORIES | I39: ="update ats_prd_master_new set ProductGroups= "&"'"&H39&"'"&"where ProductGroups="&"'"&F39&"'"&" and DPST= "&"'"&B39&"'"&"and item= "&"'"&D39&"'" -> update ats_prd_master_new set ProductGroups= 'SPARES / ACCESSORIES'where ProductGroups='SPARES / ACCESSORIES' and DPST= '90041'and item= '1332HC0803PI'
... A55: =B55&D55 -> 900401199PP002 | B55: 90040 | C55: AED - MANUFACTURED UNITS | D55: 1199PP002 | E55: CARWASHER 3HP MODELP36/30 | F55: WASHING EQUIPMENTS | H55: =IF(LEN(G55)<2,F55,G55) -> WASHING EQUIPMENTS | I55: ="update ats_prd_master_new set ProductGroups= "&"'"&H55&"'"&"where ProductGroups="&"'"&F55&"'"&" and DPST= "&"'"&B55&"'"&"and item= "&"'"&D55&"'" -> update ats_prd_master_new set ProductGroups= 'WASHING EQUIPMENTS'where ProductGroups='WASHING EQUIPMENTS' and DPST= '90040'and item= '1199PP002'
A56: =B56&D56 -> 900401199QR001 | B56: 90040 | C56: AED - MANUFACTURED UNITS | D56: 1199QR001 | E56: CAR MAT WASHER | F56: Mate Washer | G56: WASHING EQUIPMENTS | H56: =IF(LEN(G56)<2,F56,G56) -> WASHING EQUIPMENTS | I56: ="update ats_prd_master_new set ProductGroups= "&"'"&H56&"'"&"where ProductGroups="&"'"&F56&"'"&" and DPST= "&"'"&B56&"'"&"and item= "&"'"&D56&"'" -> update ats_prd_master_new set ProductGroups= 'WASHING EQUIPMENTS'where ProductGroups='Mate Washer' and DPST= '90040'and item= '1199QR001'
A57: =B57&D57 -> 90040120360320 | B57: 90040 | C57: AED - MANUFACTURED UNITS | D57: 120360320 | E57: WIRE ROPE ASSEMBLY | F57: LIFTING EQUIPMENTS | G57: LIFTING EQUIPMENTS - 2PL | H57: =IF(LEN(G57)<2,F57,G57) -> LIFTING EQUIPMENTS - 2PL | I57: ="update ats_prd_master_new set ProductGroups= "&"'"&H57&"'"&"where ProductGroups="&"'"&F57&"'"&" and DPST= "&"'"&B57&"'"&"and item= "&"'"&D57&"'" -> update ats_prd_master_new set ProductGroups= 'LIFTING EQUIPMENTS - 2PL'where ProductGroups='LIFTING EQUIPMENTS' and DPST= '90040'and item= '120360320'
A58: =B58&D58 -> 90040120367160 | B58: 90040 | C58: AED - MANUFACTURED UNITS | D58: 120367160 | E58: EP - POWER PACK ASSEMBLY | F58: WHEEL SERVICE EQUIPMENTS | H58: =IF(LEN(G58)<2,F58,G58) -> WHEEL SERVICE EQUIPMENTS | I58: ="update ats_prd_master_new set ProductGroups= "&"'"&H58&"'"&"where ProductGroups="&"'"&F58&"'"&" and DPST= "&"'"&B58&"'"&"and item= "&"'"&D58&"'" -> update ats_prd_master_new set ProductGroups= 'WHEEL SERVICE EQUIPMENTS'where ProductGroups='WHEEL SERVICE EQUIPMENTS' and DPST= '90040'and item= '120367160'
A59: =B59&D59 -> 90040120466030 | B59: 90040 | C59: AED - MANUFACTURED UNITS | D59: 120466030 | E59: KIT WHEELS FREE LIFT - S12105 | F59: LIFTING EQUIPMENTS | G59: LIFTING EQUIPMENTS - OTHERS | H59: =IF(LEN(G59)<2,F59,G59) -> LIFTING EQUIPMENTS - OTHERS | I59: ="update ats_prd_master_new set ProductGroups= "&"'"&H59&"'"&"where ProductGroups="&"'"&F59&"'"&" and DPST= "&"'"&B59&"'"&"and item= "&"'"&D59&"'" -> update ats_prd_master_new set ProductGroups= 'LIFTING EQUIPMENTS - OTHERS'where ProductGroups='LIFTING EQUIPMENTS' and DPST= '90040'and item= '120466030'
A60: =B60&D60 -> 9004012DTPP605DL | B60: 90040 | C60: AED - MANUFACTURED UNITS | D60: 12DTPP605DL | E60: PARKING LIFT SINGLE TYPE LIFT( | F60: LIFTING EQUIPMENTS | G60: LIFTING EQUIPMENTS - OTHERS | H60: =IF(LEN(G60)<2,F60,G60) -> LIFTING EQUIPMENTS - OTHERS | I60: ="update ats_prd_master_new set ProductGroups= "&"'"&H60&"'"&"where ProductGroups="&"'"&F60&"'"&" and DPST= "&"'"&B60&"'"&"and item= "&"'"&D60&"'" -> update ats_prd_master_new set ProductGroups= 'LIFTING EQUIPMENTS - OTHERS'where ProductGroups='LIFTING EQUIPMENTS' and DPST= '90040'and item= '12DTPP605DL'
A61: =B61&D61 -> 9004012DTPP606DL | B61: 90040 | C61: AED - MANUFACTURED UNITS | D61: 12DTPP606DL | E61: PARKING LIFT COMBINED TYPE LIF | F61: LIFTING EQUIPMENTS | G61: LIFTING EQUIPMENTS - OTHERS | H61: =IF(LEN(G61)<2,F61,G61) -> LIFTING EQUIPMENTS - OTHERS | I61: ="update ats_prd_master_new set ProductGroups= "&"'"&H61&"'"&"where ProductGroups="&"'"&F61&"'"&" and DPST= "&"'"&B61&"'"&"and item= "&"'"&D61&"'" -> update ats_prd_master_new set ProductGroups= 'LIFTING EQUIPMENTS - OTHERS'where ProductGroups='LIFTING EQUIPMENTS' and DPST= '90040'and item= '12DTPP606DL'
A62: =B62&D62 -> 9004013032834A | B62: 90040 | C62: AED - MANUFACTURED UNITS | D62: 13032834A | E62: HOSE ASSY OIL 1.1MT | F62: LUBE EQUIPMENTS | H62: =IF(LEN(G62)<2,F62,G62) -> LUBE EQUIPMENTS | I62: ="update ats_prd_master_new set ProductGroups= "&"'"&H62&"'"&"where ProductGroups="&"'"&F62&"'"&" and DPST= "&"'"&B62&"'"&"and item= "&"'"&D62&"'" -> update ats_prd_master_new set ProductGroups= 'LUBE EQUIPMENTS'where ProductGroups='LUBE EQUIPMENTS' and DPST= '90040'and item= '13032834A'
A63: =B63&D63 -> 90040130450190 | B63: 90040 | C63: AED - MANUFACTURED UNITS | D63: 130450190 | E63: PIPE ASSY; RISER | F63: SPARES / ACCESSORIES | H63: =IF(LEN(G63)<2,F63,G63) -> SPARES / ACCESSORIES | I63: ="update ats_prd_master_new set ProductGroups= "&"'"&H63&"'"&"where ProductGroups="&"'"&F63&"'"&" and DPST= "&"'"&B63&"'"&"and item= "&"'"&D63&"'" -> update ats_prd_master_new set ProductGroups= 'SPARES / ACCESSORIES'where ProductGroups='SPARES / ACCESSORIES' and DPST= '90040'and item= '130450190'
A64: =B64&D64 -> 90040150482210 | B64: 90040 | C64: AED - MANUFACTURED UNITS | D64: 150482210 | E64: FILTERS AND REGULATOR ASSY | F64: TYRE INFLATORS | H64: =IF(LEN(G64)<2,F64,G64) -> TYRE INFLATORS | I64: ="update ats_prd_master_new set ProductGroups= "&"'"&H64&"'"&"where ProductGroups="&"'"&F64&"'"&" and DPST= "&"'"&B64&"'"&"and item= "&"'"&D64&"'" -> update ats_prd_master_new set ProductGroups= 'TYRE INFLATORS'where ProductGroups='TYRE INFLATORS' and DPST= '90040'and item= '150482210'
A65: =B65&D65 -> 900401699EL005 | B65: 90040 | C65: AED - MANUFACTURED UNITS | D65: 1699EL005 | E65: W&D VACUUM CLEANER - 1M | F65: WASHING EQUIPMENTS | H65: =IF(LEN(G65)<2,F65,G65) -> WASHING EQUIPMENTS | I65: ="update ats_prd_master_new set ProductGroups= "&"'"&H65&"'"&"where ProductGroups="&"'"&F65&"'"&" and DPST= "&"'"&B65&"'"&"and item= "&"'"&D65&"'" -> update ats_prd_master_new set ProductGroups= 'WASHING EQUIPMENTS'where ProductGroups='WASHING EQUIPMENTS' and DPST= '90040'and item= '1699EL005'
A66: =B66&D66 -> 90040200320440 | B66: 90040 | C66: AED - MANUFACTURED UNITS | D66: 200320440 | E66: TYRE CHANGER-STANDARD | F66: WHEEL SERVICE EQUIPMENTS | H66: =IF(LEN(G66)<2,F66,G66) -> WHEEL SERVICE EQUIPMENTS | I66: ="update ats_prd_master_new set ProductGroups= "&"'"&H66&"'"&"where ProductGroups="&"'"&F66&"'"&" and DPST= "&"'"&B66&"'"&"and item= "&"'"&D66&"'" -> update ats_prd_master_new set ProductGroups= 'WHEEL SERVICE EQUIPMENTS'where ProductGroups='WHEEL SERVICE EQUIPMENTS' and DPST= '90040'and item= '200320440'
A67: =B67&D67 -> 90040200320490 | B67: 90040 | C67: AED - MANUFACTURED UNITS | D67: 200320490 | E67: TYRE CHANGER-CV | F67: WHEEL SERVICE EQUIPMENTS | H67: =IF(LEN(G67)<2,F67,G67) -> WHEEL SERVICE EQUIPMENTS | I67: ="update ats_prd_master_new set ProductGroups= "&"'"&H67&"'"&"where ProductGroups="&"'"&F67&"'"&" and DPST= "&"'"&B67&"'"&"and item= "&"'"&D67&"'" -> update ats_prd_master_new set ProductGroups= 'WHEEL SERVICE EQUIPMENTS'where ProductGroups='WHEEL SERVICE EQUIPMENTS' and DPST= '90040'and item= '200320490'
A68: =B68&D68 -> 90040200320650 | B68: 90040 | C68: AED - MANUFACTURED UNITS | D68: 200320650 | E68: TYRE CHANGER STANDARD NEX | F68: WHEEL SERVICE EQUIPMENTS | H68: =IF(LEN(G68)<2,F68,G68) -> WHEEL SERVICE EQUIPMENTS | I68: ="update ats_prd_master_new set ProductGroups= "&"'"&H68&"'"&"where ProductGroups="&"'"&F68&"'"&" and DPST= "&"'"&B68&"'"&"and item= "&"'"&D68&"'" -> update ats_prd_master_new set ProductGroups= 'WHEEL SERVICE EQUIPMENTS'where ProductGroups='WHEEL SERVICE EQUIPMENTS' and DPST= '90040'and item= '200320650'
A69: =B69&D69 -> 900402399BR001 | B69: 90040 | C69: AED - MANUFACTURED UNITS | D69: 2399BR001 | E69: WHEEL BALANCER DIGITAL-DWB SP | F69: WHEEL SERVICE EQUIPMENTS | H69: =IF(LEN(G69)<2,F69,G69) -> WHEEL SERVICE EQUIPMENTS | I69: ="update ats_prd_master_new set ProductGroups= "&"'"&H69&"'"&"where ProductGroups="&"'"&F69&"'"&" and DPST= "&"'"&B69&"'"&"and item= "&"'"&D69&"'" -> update ats_prd_master_new set ProductGroups= 'WHEEL SERVICE EQUIPMENTS'where ProductGroups='WHEEL SERVICE EQUIPMENTS' and DPST= '90040'and item= '2399BR001'
A70: =B70&D70 -> 900402399BR005 | B70: 90040 | C70: AED - MANUFACTURED UNITS | D70: 2399BR005 | E70: WHEEL BALANCER VIDEO GRAPHIC | F70: WHEEL SERVICE EQUIPMENTS | H70: =IF(LEN(G70)<2,F70,G70) -> WHEEL SERVICE EQUIPMENTS | I70: ="update ats_prd_master_new set ProductGroups= "&"'"&H70&"'"&"where ProductGroups="&"'"&F70&"'"&" and DPST= "&"'"&B70&"'"&"and item= "&"'"&D70&"'" -> update ats_prd_master_new set ProductGroups= 'WHEEL SERVICE EQUIPMENTS'where ProductGroups='WHEEL SERVICE EQUIPMENTS' and DPST= '90040'and item= '2399BR005'
A71: =B71&D71 -> 900402399CE008 | B71: 90040 | C71: AED - MANUFACTURED UNITS | D71: 2399CE008 | E71: HAND SPIN WHEEL BALANCER | F71: MMS | H71: =IF(LEN(G71)<2,F71,G71) -> MMS | I71: ="update ats_prd_master_new set ProductGroups= "&"'"&H71&"'"&"where ProductGroups="&"'"&F71&"'"&" and DPST= "&"'"&B71&"'"&"and item= "&"'"&D71&"'" -> update ats_prd_master_new set ProductGroups= 'MMS'where ProductGroups='MMS' and DPST= '90040'and item= '2399CE008'
A72: =B72&D72 -> 90040250300510 | B72: 90040 | C72: AED - MANUFACTURED UNITS | D72: 250300510 | E72: COMPRESSOR ASSEMBLY | F72: SPARES / ACCESSORIES | H72: =IF(LEN(G72)<2,F72,G72) -> SPARES / ACCESSORIES | I72: ="update ats_prd_master_new set ProductGroups= "&"'"&H72&"'"&"where ProductGroups="&"'"&F72&"'"&" and DPST= "&"'"&B72&"'"&"and item= "&"'"&D72&"'" -> update ats_prd_master_new set ProductGroups= 'SPARES / ACCESSORIES'where ProductGroups='SPARES / ACCESSORIES' and DPST= '90040'and item= '250300510'
A73: =B73&D73 -> 900403603IRS00 | B73: 90040 | C73: AED - MANUFACTURED UNITS | D73: 3603IRS00 | E73: JAI6276L 1 SUPPER DUTY IMPACT | F73: PNEUMATIC TOOLS | H73: =IF(LEN(G73)<2,F73,G73) -> PNEUMATIC TOOLS | I73: ="update ats_prd_master_new set ProductGroups= "&"'"&H73&"'"&"where ProductGroups="&"'"&F73&"'"&" and DPST= "&"'"&B73&"'"&"and item= "&"'"&D73&"'" -> update ats_prd_master_new set ProductGroups= 'PNEUMATIC TOOLS'where ProductGroups='PNEUMATIC TOOLS' and DPST= '90040'and item= '3603IRS00'
... A78: =B78&D78 -> 900403899YS009 | B78: 90040 | C78: AED - MANUFACTURED UNITS | D78: 3899YS009 | E78: ACER PC WITH 18.5"TFT MONITOR | F78: WHEEL SERVICE EQUIPMENTS | H78: =IF(LEN(G78)<2,F78,G78) -> WHEEL SERVICE EQUIPMENTS | I78: ="update ats_prd_master_new set ProductGroups= "&"'"&H78&"'"&"where ProductGroups="&"'"&F78&"'"&" and DPST= "&"'"&B78&"'"&"and item= "&"'"&D78&"'" -> update ats_prd_master_new set ProductGroups= 'WHEEL SERVICE EQUIPMENTS'where ProductGroups='WHEEL SERVICE EQUIPMENTS' and DPST= '90040'and item= '3899YS009'
A79: =B79&D79 -> 90040460338140 | B79: 90040 | C79: AED - MANUFACTURED UNITS | D79: 460338140 | E79: AIR HANDLING UNIT HY. | F79: BODY SHOP & PAINT EQUIPMENTS | G79: BODY SHOP & PAINT EQUIPMENTS - PB | H79: =IF(LEN(G79)<2,F79,G79) -> BODY SHOP & PAINT EQUIPMENTS - PB | I79: ="update ats_prd_master_new set ProductGroups= "&"'"&H79&"'"&"where ProductGroups="&"'"&F79&"'"&" and DPST= "&"'"&B79&"'"&"and item= "&"'"&D79&"'" -> update ats_prd_master_new set ProductGroups= 'BODY SHOP & PAINT EQUIPMENTS - PB'where ProductGroups='BODY SHOP & PAINT EQUIPMENTS' and DPST= '90040'and item= '460338140'
A80: =B80&D80 -> 900404899SZ002 | B80: 90040 | C80: AED - MANUFACTURED UNITS | D80: 4899SZ002 | E80: CRS CLAMP ART 134 | F80: BODY SHOP & PAINT EQUIPMENTS | G80: BODY SHOP & PAINT EQUIPMENTS - CRS | H80: =IF(LEN(G80)<2,F80,G80) -> BODY SHOP & PAINT EQUIPMENTS - CRS | I80: ="update ats_prd_master_new set ProductGroups= "&"'"&H80&"'"&"where ProductGroups="&"'"&F80&"'"&" and DPST= "&"'"&B80&"'"&"and item= "&"'"&D80&"'" -> update ats_prd_master_new set ProductGroups= 'BODY SHOP & PAINT EQUIPMENTS - CRS'where ProductGroups='BODY SHOP & PAINT EQUIPMENTS' and DPST= '90040'and item= '4899SZ002'
A81: =B81&D81 -> 900404899SZ007 | B81: 90040 | C81: AED - MANUFACTURED UNITS | D81: 4899SZ007 | E81: CRS CLAMP 90 DEGREE ART 133 | F81: BODY SHOP & PAINT EQUIPMENTS | G81: BODY SHOP & PAINT EQUIPMENTS - CRS | H81: =IF(LEN(G81)<2,F81,G81) -> BODY SHOP & PAINT EQUIPMENTS - CRS | I81: ="update ats_prd_master_new set ProductGroups= "&"'"&H81&"'"&"where ProductGroups="&"'"&F81&"'"&" and DPST= "&"'"&B81&"'"&"and item= "&"'"&D81&"'" -> update ats_prd_master_new set ProductGroups= 'BODY SHOP & PAINT EQUIPMENTS - CRS'where ProductGroups='BODY SHOP & PAINT EQUIPMENTS' and DPST= '90040'and item= '4899SZ007'
A82: =B82&D82 -> 900404899SZ010 | B82: 90040 | C82: AED - MANUFACTURED UNITS | D82: 4899SZ010 | E82: CRS PULLER BOOMERANG ART 138 | F82: BODY SHOP & PAINT EQUIPMENTS | G82: BODY SHOP & PAINT EQUIPMENTS - CRS | H82: =IF(LEN(G82)<2,F82,G82) -> BODY SHOP & PAINT EQUIPMENTS - CRS | I82: ="update ats_prd_master_new set ProductGroups= "&"'"&H82&"'"&"where ProductGroups="&"'"&F82&"'"&" and DPST= "&"'"&B82&"'"&"and item= "&"'"&D82&"'" -> update ats_prd_master_new set ProductGroups= 'BODY SHOP & PAINT EQUIPMENTS - CRS'where ProductGroups='BODY SHOP & PAINT EQUIPMENTS' and DPST= '90040'and item= '4899SZ010'
A83: =B83&D83 -> 900404899SZ012 | B83: 90040 | C83: AED - MANUFACTURED UNITS | D83: 4899SZ012 | E83: CRS MULTI HOLE PLATE ART 123 | F83: BODY SHOP & PAINT EQUIPMENTS | G83: BODY SHOP & PAINT EQUIPMENTS - CRS | H83: =IF(LEN(G83)<2,F83,G83) -> BODY SHOP & PAINT EQUIPMENTS - CRS | I83: ="update ats_prd_master_new set ProductGroups= "&"'"&H83&"'"&"where ProductGroups="&"'"&F83&"'"&" and DPST= "&"'"&B83&"'"&"and item= "&"'"&D83&"'" -> update ats_prd_master_new set ProductGroups= 'BODY SHOP & PAINT EQUIPMENTS - CRS'where ProductGroups='BODY SHOP & PAINT EQUIPMENTS' and DPST= '90040'and item= '4899SZ012'
A84: =B84&D84 -> 900404899SZ015 | B84: 90040 | C84: AED - MANUFACTURED UNITS | D84: 4899SZ015 | E84: CRS STRAPS ART 900/901 | F84: BODY SHOP & PAINT EQUIPMENTS | G84: BODY SHOP & PAINT EQUIPMENTS - CRS | H84: =IF(LEN(G84)<2,F84,G84) -> BODY SHOP & PAINT EQUIPMENTS - CRS | I84: ="update ats_prd_master_new set ProductGroups= "&"'"&H84&"'"&"where ProductGroups="&"'"&F84&"'"&" and DPST= "&"'"&B84&"'"&"and item= "&"'"&D84&"'" -> update ats_prd_master_new set ProductGroups= 'BODY SHOP & PAINT EQUIPMENTS - CRS'where ProductGroups='BODY SHOP & PAINT EQUIPMENTS' and DPST= '90040'and item= '4899SZ015'
A85: =B85&D85 -> 90040870400020 | B85: 90040 | C85: AED - MANUFACTURED UNITS | D85: 870400020 | E85: DISH BLANK OD 750X5THK | F85: PVD SALES | H85: =IF(LEN(G85)<2,F85,G85) -> PVD SALES | I85: ="update ats_prd_master_new set ProductGroups= "&"'"&H85&"'"&"where ProductGroups="&"'"&F85&"'"&" and DPST= "&"'"&B85&"'"&"and item= "&"'"&D85&"'" -> update ats_prd_master_new set ProductGroups= 'PVD SALES'where ProductGroups='PVD SALES' and DPST= '90040'and item= '870400020'
A86: =B86&D86 -> 90040870400030 | B86: 90040 | C86: AED - MANUFACTURED UNITS | D86: 870400030 | E86: 220 SHELL | F86: PVD SALES | H86: =IF(LEN(G86)<2,F86,G86) -> PVD SALES | I86: ="update ats_prd_master_new set ProductGroups= "&"'"&H86&"'"&"where ProductGroups="&"'"&F86&"'"&" and DPST= "&"'"&B86&"'"&"and item= "&"'"&D86&"'" -> update ats_prd_master_new set ProductGroups= 'PVD SALES'where ProductGroups='PVD SALES' and DPST= '90040'and item= '870400030'
A87: =B87&D87 -> 900409099PS001 | B87: 90040 | C87: AED - MANUFACTURED UNITS | D87: 9099PS001 | E87: INVERTOR SPOT WELDER i4 | F87: BODY SHOP & PAINT EQUIPMENTS | G87: BODY SHOP & PAINT EQUIPMENTS - WELDERS | H87: =IF(LEN(G87)<2,F87,G87) -> BODY SHOP & PAINT EQUIPMENTS - WELDERS | I87: ="update ats_prd_master_new set ProductGroups= "&"'"&H87&"'"&"where ProductGroups="&"'"&F87&"'"&" and DPST= "&"'"&B87&"'"&"and item= "&"'"&D87&"'" -> update ats_prd_master_new set ProductGroups= 'BODY SHOP & PAINT EQUIPMENTS - WELDERS'where ProductGroups='BODY SHOP & PAINT EQUIPMENTS' and DPST= '90040'and item= '9099PS001'
A88: =B88&D88 -> 90040K12990017 | B88: 90040 | C88: AED - MANUFACTURED UNITS | D88: K12990017 | E88: DSHL - 3.0 SUV ADAPTOR KIT | F88: LIFTING EQUIPMENTS | G88: LIFTING EQUIPMENTS - SCISSOR LIFT | H88: =IF(LEN(G88)<2,F88,G88) -> LIFTING EQUIPMENTS - SCISSOR LIFT | I88: ="update ats_prd_master_new set ProductGroups= "&"'"&H88&"'"&"where ProductGroups="&"'"&F88&"'"&" and DPST= "&"'"&B88&"'"&"and item= "&"'"&D88&"'" -> update ats_prd_master_new set ProductGroups= 'LIFTING EQUIPMENTS - SCISSOR LIFT'where ProductGroups='LIFTING EQUIPMENTS' and DPST= '90040'and item= 'K12990017'
A89: =B89&D89 -> 900411332HC2503PI | B89: 90041 | C89: AED - SPARES | D89: 1332HC2503PI | E89: EXTENTION FUNNEL | F89: SPARES / ACCESSORIES | H89: =IF(LEN(G89)<2,F89,G89) -> SPARES / ACCESSORIES | I89: ="update ats_prd_master_new set ProductGroups= "&"'"&H89&"'"&"where ProductGroups="&"'"&F89&"'"&" and DPST= "&"'"&B89&"'"&"and item= "&"'"&D89&"'" -> update ats_prd_master_new set ProductGroups= 'SPARES / ACCESSORIES'where ProductGroups='SPARES / ACCESSORIES' and DPST= '90041'and item= '1332HC2503PI'
A90: =B90&D90 -> 90041200320490 | B90: 90041 | C90: AED - SPARES | D90: 200320490 | E90: TYRE CHANGER-CV | F90: SPARES / ACCESSORIES | H90: =IF(LEN(G90)<2,F90,G90) -> SPARES / ACCESSORIES | I90: ="update ats_prd_master_new set ProductGroups= "&"'"&H90&"'"&"where ProductGroups="&"'"&F90&"'"&" and DPST= "&"'"&B90&"'"&"and item= "&"'"&D90&"'" -> update ats_prd_master_new set ProductGroups= 'SPARES / ACCESSORIES'where ProductGroups='SPARES / ACCESSORIES' and DPST= '90041'and item= '200320490'
A91: =B91&D91 -> 90040K12990018 | B91: 90040 | C91: AED - MANUFACTURED UNITS | D91: K12990018 | E91: DSHL - 3.0 ABOVE GROUND VERSI | F91: LIFTING EQUIPMENTS | G91: LIFTING EQUIPMENTS - SCISSOR LIFT | H91: =IF(LEN(G91)<2,F91,G91) -> LIFTING EQUIPMENTS - SCISSOR LIFT | I91: ="update ats_prd_master_new set ProductGroups= "&"'"&H91&"'"&"where ProductGroups="&"'"&F91&"'"&" and DPST= "&"'"&B91&"'"&"and item= "&"'"&D91&"'" -> update ats_prd_master_new set ProductGroups= 'LIFTING EQUIPMENTS - SCISSOR LIFT'where ProductGroups='LIFTING EQUIPMENTS' and DPST= '90040'and item= 'K12990018'
A92: =B92&D92 -> 90041390016MP | B92: 90041 | C92: AED - SPARES | D92: 390016MP | E92: SWING BOLTS,NUT,WASHER | F92: SPARES / ACCESSORIES | H92: =IF(LEN(G92)<2,F92,G92) -> SPARES / ACCESSORIES | I92: ="update ats_prd_master_new set ProductGroups= "&"'"&H92&"'"&"where ProductGroups="&"'"&F92&"'"&" and DPST= "&"'"&B92&"'"&"and item= "&"'"&D92&"'" -> update ats_prd_master_new set ProductGroups= 'SPARES / ACCESSORIES'where ProductGroups='SPARES / ACCESSORIES' and DPST= '90041'and item= '390016MP'
A93: =B93&D93 -> 90041390037MP | B93: 90041 | C93: AED - SPARES | D93: 390037MP | E93: M16X50 BOLT,NUT,WASHER | F93: SPARES / ACCESSORIES | H93: =IF(LEN(G93)<2,F93,G93) -> SPARES / ACCESSORIES | I93: ="update ats_prd_master_new set ProductGroups= "&"'"&H93&"'"&"where ProductGroups="&"'"&F93&"'"&" and DPST= "&"'"&B93&"'"&"and item= "&"'"&D93&"'" -> update ats_prd_master_new set ProductGroups= 'SPARES / ACCESSORIES'where ProductGroups='SPARES / ACCESSORIES' and DPST= '90041'and item= '390037MP'
A94: =B94&D94 -> 90040K12990019 | B94: 90040 | C94: AED - MANUFACTURED UNITS | D94: K12990019 | E94: DSHL - 3.0 INGROUND VERSION K | F94: LIFTING EQUIPMENTS | G94: LIFTING EQUIPMENTS - SCISSOR LIFT | H94: =IF(LEN(G94)<2,F94,G94) -> LIFTING EQUIPMENTS - SCISSOR LIFT | I94: ="update ats_prd_master_new set ProductGroups= "&"'"&H94&"'"&"where ProductGroups="&"'"&F94&"'"&" and DPST= "&"'"&B94&"'"&"and item= "&"'"&D94&"'" -> update ats_prd_master_new set ProductGroups= 'LIFTING EQUIPMENTS - SCISSOR LIFT'where ProductGroups='LIFTING EQUIPMENTS' and DPST= '90040'and item= 'K12990019'
A95: =B95&D95 -> 90041390038MP | B95: 90041 | C95: AED - SPARES | D95: 390038MP | E95: M12X40 FOUNDATION BOLT,NUT,WAR | F95: SPARES / ACCESSORIES | H95: =IF(LEN(G95)<2,F95,G95) -> SPARES / ACCESSORIES | I95: ="update ats_prd_master_new set ProductGroups= "&"'"&H95&"'"&"where ProductGroups="&"'"&F95&"'"&" and DPST= "&"'"&B95&"'"&"and item= "&"'"&D95&"'" -> update ats_prd_master_new set ProductGroups= 'SPARES / ACCESSORIES'where ProductGroups='SPARES / ACCESSORIES' and DPST= '90041'and item= '390038MP'
A96: =B96&D96 -> 90041390039MP | B96: 90041 | C96: AED - SPARES | D96: 390039MP | E96: M10X20 FOUNDATION BOLT,NUT,WAR | F96: SPARES / ACCESSORIES | H96: =IF(LEN(G96)<2,F96,G96) -> SPARES / ACCESSORIES | I96: ="update ats_prd_master_new set ProductGroups= "&"'"&H96&"'"&"where ProductGroups="&"'"&F96&"'"&" and DPST= "&"'"&B96&"'"&"and item= "&"'"&D96&"'" -> update ats_prd_master_new set ProductGroups= 'SPARES / ACCESSORIES'where ProductGroups='SPARES / ACCESSORIES' and DPST= '90041'and item= '390039MP'
A97: =B97&D97 -> 90040K13990007 | B97: 90040 | C97: AED - MANUFACTURED UNITS | D97: K13990007 | E97: KIT FOR 1:3 OIL PUMP 210 LITRE | F97: LUBE EQUIPMENTS | H97: =IF(LEN(G97)<2,F97,G97) -> LUBE EQUIPMENTS | I97: ="update ats_prd_master_new set ProductGroups= "&"'"&H97&"'"&"where ProductGroups="&"'"&F97&"'"&" and DPST= "&"'"&B97&"'"&"and item= "&"'"&D97&"'" -> update ats_prd_master_new set ProductGroups= 'LUBE EQUIPMENTS'where ProductGroups='LUBE EQUIPMENTS' and DPST= '90040'and item= 'K13990007'
A98: =B98&D98 -> 90040M600004954 | B98: 90040 | C98: AED - MANUFACTURED UNITS | D98: M600004954 | E98: ELGI HOIST LUBE 185 LITRES | F98: LUBE EQUIPMENTS | H98: =IF(LEN(G98)<2,F98,G98) -> LUBE EQUIPMENTS | I98: ="update ats_prd_master_new set ProductGroups= "&"'"&H98&"'"&"where ProductGroups="&"'"&F98&"'"&" and DPST= "&"'"&B98&"'"&"and item= "&"'"&D98&"'" -> update ats_prd_master_new set ProductGroups= 'LUBE EQUIPMENTS'where ProductGroups='LUBE EQUIPMENTS' and DPST= '90040'and item= 'M600004954'
A99: =B99&D99 -> 90040S11003 | B99: 90040 | C99: AED - MANUFACTURED UNITS | D99: S11003 | E99: LL 03 022 EP 3HP 350 150 L | F99: WASHING EQUIPMENTS | H99: =IF(LEN(G99)<2,F99,G99) -> WASHING EQUIPMENTS | I99: ="update ats_prd_master_new set ProductGroups= "&"'"&H99&"'"&"where ProductGroups="&"'"&F99&"'"&" and DPST= "&"'"&B99&"'"&"and item= "&"'"&D99&"'" -> update ats_prd_master_new set ProductGroups= 'WASHING EQUIPMENTS'where ProductGroups='WASHING EQUIPMENTS' and DPST= '90040'and item= 'S11003'
A100: =B100&D100 -> 9004139WW200017WE | B100: 90041 | C100: AED - SPARES | D100: 39WW200017WE | E100: GASKET FOR PSF/ASP FLANGE | F100: SPARES / ACCESSORIES | H100: =IF(LEN(G100)<2,F100,G100) -> SPARES / ACCESSORIES | I100: ="update ats_prd_master_new set ProductGroups= "&"'"&H100&"'"&"where ProductGroups="&"'"&F100&"'"&" and DPST= "&"'"&B100&"'"&"and item= "&"'"&D100&"'" -> update ats_prd_master_new set ProductGroups= 'SPARES / ACCESSORIES'where ProductGroups='SPARES / ACCESSORIES' and DPST= '90041'and item= '39WW200017WE'
A101: =B101&D101 -> 9004139WW200018WE | B101: 90041 | C101: AED - SPARES | D101: 39WW200018WE | E101: GASKET FOR 1" PIPING FLANGE | F101: SPARES / ACCESSORIES | H101: =IF(LEN(G101)<2,F101,G101) -> SPARES / ACCESSORIES | I101: ="update ats_prd_master_new set ProductGroups= "&"'"&H101&"'"&"where ProductGroups="&"'"&F101&"'"&" and DPST= "&"'"&B101&"'"&"and item= "&"'"&D101&"'" -> update ats_prd_master_new set ProductGroups= 'SPARES / ACCESSORIES'where ProductGroups='SPARES / ACCESSORIES' and DPST= '90041'and item= '39WW200018WE'
A102: =B102&D102 -> 90040S11004 | B102: 90040 | C102: AED - MANUFACTURED UNITS | D102: S11004 | E102: LL 03 022 EP 3HP 350 BASE | F102: WASHING EQUIPMENTS | H102: =IF(LEN(G102)<2,F102,G102) -> WASHING EQUIPMENTS | I102: ="update ats_prd_master_new set ProductGroups= "&"'"&H102&"'"&"where ProductGroups="&"'"&F102&"'"&" and DPST= "&"'"&B102&"'"&"and item= "&"'"&D102&"'" -> update ats_prd_master_new set ProductGroups= 'WASHING EQUIPMENTS'where ProductGroups='WASHING EQUIPMENTS' and DPST= '90040'and item= 'S11004'
A103: =B103&D103 -> 90044870401200 | B103: 90044 | C103: AED-SPECIAL PROJECTS | D103: 870401200 | E103: GROUP-3 | F103: PVD SALES | H103: =IF(LEN(G103)<2,F103,G103) -> PVD SALES | I103: ="update ats_prd_master_new set ProductGroups= "&"'"&H103&"'"&"where ProductGroups="&"'"&F103&"'"&" and DPST= "&"'"&B103&"'"&"and item= "&"'"&D103&"'" -> update ats_prd_master_new set ProductGroups= 'PVD SALES'where ProductGroups='PVD SALES' and DPST= '90044'and item= '870401200'
A104: =B104&D104 -> 90040Z12113 | B104: 90040 | C104: AED - MANUFACTURED UNITS | D104: Z12113 | E104: TWO POST HYD LIFT | F104: LIFTING EQUIPMENTS | G104: LIFTING EQUIPMENTS - 2PL | H104: =IF(LEN(G104)<2,F104,G104) -> LIFTING EQUIPMENTS - 2PL | I104: ="update ats_prd_master_new set ProductGroups= "&"'"&H104&"'"&"where ProductGroups="&"'"&F104&"'"&" and DPST= "&"'"&B104&"'"&"and item= "&"'"&D104&"'" -> update ats_prd_master_new set ProductGroups= 'LIFTING EQUIPMENTS - 2PL'where ProductGroups='LIFTING EQUIPMENTS' and DPST= '90040'and item= 'Z12113'
A105: =B105&D105 -> 90040S11014 | B105: 90040 | C105: AED - MANUFACTURED UNITS | D105: S11014 | E105: AUTO CAR WASH EQUIPMENT | F105: ACW | H105: =IF(LEN(G105)<2,F105,G105) -> ACW | I105: ="update ats_prd_master_new set ProductGroups= "&"'"&H105&"'"&"where ProductGroups="&"'"&F105&"'"&" and DPST= "&"'"&B105&"'"&"and item= "&"'"&D105&"'" -> update ats_prd_master_new set ProductGroups= 'ACW'where ProductGroups='ACW' and DPST= '90040'and item= 'S11014'
A106: =B106&D106 -> 90041000906221 | B106: 90041 | C106: AED - SPARES | D106: 000906221 | E106: BOLT;HEX;M16 X 75 FULL THREAD | F106: SPARES / ACCESSORIES | H106: =IF(LEN(G106)<2,F106,G106) -> SPARES / ACCESSORIES | I106: ="update ats_prd_master_new set ProductGroups= "&"'"&H106&"'"&"where ProductGroups="&"'"&F106&"'"&" and DPST= "&"'"&B106&"'"&"and item= "&"'"&D106&"'" -> update ats_prd_master_new set ProductGroups= 'SPARES / ACCESSORIES'where ProductGroups='SPARES / ACCESSORIES' and DPST= '90041'and item= '000906221'
A107: =B107&D107 -> 90042K48990009 | B107: 90042 | C107: AED - TRADED UNITS | D107: K48990009 | E107: DENT PULLING SYSTEM MS W TROLL | F107: BODY SHOP & PAINT EQUIPMENTS | G107: BODY SHOP & PAINT EQUIPMENTS - PANEL REPAIR | H107: =IF(LEN(G107)<2,F107,G107) -> BODY SHOP & PAINT EQUIPMENTS - PANEL REPAIR | I107: ="update ats_prd_master_new set ProductGroups= "&"'"&H107&"'"&"where ProductGroups="&"'"&F107&"'"&" and DPST= "&"'"&B107&"'"&"and item= "&"'"&D107&"'" -> update ats_prd_master_new set ProductGroups= 'BODY SHOP & PAINT EQUIPMENTS - PANEL REPAIR'where ProductGroups='BODY SHOP & PAINT EQUIPMENTS' and DPST= '90042'and item= 'K48990009'
A108: =B108&D108 -> 90040S11015 | B108: 90040 | C108: AED - MANUFACTURED UNITS | D108: S11015 | E108: TRIPLE PLUNGER PUMP - 3HP | F108: WASHING EQUIPMENTS | H108: =IF(LEN(G108)<2,F108,G108) -> WASHING EQUIPMENTS | I108: ="update ats_prd_master_new set ProductGroups= "&"'"&H108&"'"&"where ProductGroups="&"'"&F108&"'"&" and DPST= "&"'"&B108&"'"&"and item= "&"'"&D108&"'" -> update ats_prd_master_new set ProductGroups= 'WASHING EQUIPMENTS'where ProductGroups='WASHING EQUIPMENTS' and DPST= '90040'and item= 'S11015'
A109: =B109&D109 -> 90240S11030 | B109: 90240 | C109: AED - UNITS - INTERNATIONAL | D109: S11030 | E109: WASHKIT-SP W/O BOOM | F109: International Sales | H109: =IF(LEN(G109)<2,F109,G109) -> International Sales | I109: ="update ats_prd_master_new set ProductGroups= "&"'"&H109&"'"&"where ProductGroups="&"'"&F109&"'"&" and DPST= "&"'"&B109&"'"&"and item= "&"'"&D109&"'" -> update ats_prd_master_new set ProductGroups= 'International Sales'where ProductGroups='International Sales' and DPST= '90240'and item= 'S11030'
A110: =B110&D110 -> 90040S11016 | B110: 90040 | C110: AED - MANUFACTURED UNITS | D110: S11016 | E110: UNDERCHASSIS WASH EQUIPMENT | F110: UCW | H110: =IF(LEN(G110)<2,F110,G110) -> UCW | I110: ="update ats_prd_master_new set ProductGroups= "&"'"&H110&"'"&"where ProductGroups="&"'"&F110&"'"&" and DPST= "&"'"&B110&"'"&"and item= "&"'"&D110&"'" -> update ats_prd_master_new set ProductGroups= 'UCW'where ProductGroups='UCW' and DPST= '90040'and item= 'S11016'
A111: =B111&D111 -> 90040S11017 | B111: 90040 | C111: AED - MANUFACTURED UNITS | D111: S11017 | E111: TPP SAFETY VALVE MODEL | F111: WASHING EQUIPMENTS | H111: =IF(LEN(G111)<2,F111,G111) -> WASHING EQUIPMENTS | I111: ="update ats_prd_master_new set ProductGroups= "&"'"&H111&"'"&"where ProductGroups="&"'"&F111&"'"&" and DPST= "&"'"&B111&"'"&"and item= "&"'"&D111&"'" -> update ats_prd_master_new set ProductGroups= 'WASHING EQUIPMENTS'where ProductGroups='WASHING EQUIPMENTS' and DPST= '90040'and item= 'S11017'
A112: =B112&D112 -> 90040S11019 | B112: 90040 | C112: AED - MANUFACTURED UNITS | D112: S11019 | E112: TOUCHLESS CAR WASHER - STORM | F112: TCW | H112: =IF(LEN(G112)<2,F112,G112) -> TCW | I112: ="update ats_prd_master_new set ProductGroups= "&"'"&H112&"'"&"where ProductGroups="&"'"&F112&"'"&" and DPST= "&"'"&B112&"'"&"and item= "&"'"&D112&"'" -> update ats_prd_master_new set ProductGroups= 'TCW'where ProductGroups='TCW' and DPST= '90040'and item= 'S11019'
A113: =B113&D113 -> 90040S11022 | B113: 90040 | C113: AED - MANUFACTURED UNITS | D113: S11022 | E113: UNDER CHASSIS WASHER - NEW GEN | F113: UCW | H113: =IF(LEN(G113)<2,F113,G113) -> UCW | I113: ="update ats_prd_master_new set ProductGroups= "&"'"&H113&"'"&"where ProductGroups="&"'"&F113&"'"&" and DPST= "&"'"&B113&"'"&"and item= "&"'"&D113&"'" -> update ats_prd_master_new set ProductGroups= 'UCW'where ProductGroups='UCW' and DPST= '90040'and item= 'S11022'
A114: =B114&D114 -> 90040S11023 | B114: 90040 | C114: AED - MANUFACTURED UNITS | D114: S11023 | E114: TOUCHLESS CAR WASHER - STORM | F114: TCW | H114: =IF(LEN(G114)<2,F114,G114) -> TCW | I114: ="update ats_prd_master_new set ProductGroups= "&"'"&H114&"'"&"where ProductGroups="&"'"&F114&"'"&" and DPST= "&"'"&B114&"'"&"and item= "&"'"&D114&"'" -> update ats_prd_master_new set ProductGroups= 'TCW'where ProductGroups='TCW' and DPST= '90040'and item= 'S11023'
A115: =B115&D115 -> 90040S11024 | B115: 90040 | C115: AED - MANUFACTURED UNITS | D115: S11024 | E115: WASH BOOM | F115: WASHING EQUIPMENTS | H115: =IF(LEN(G115)<2,F115,G115) -> WASHING EQUIPMENTS | I115: ="update ats_prd_master_new set ProductGroups= "&"'"&H115&"'"&"where ProductGroups="&"'"&F115&"'"&" and DPST= "&"'"&B115&"'"&"and item= "&"'"&D115&"'" -> update ats_prd_master_new set ProductGroups= 'WASHING EQUIPMENTS'where ProductGroups='WASHING EQUIPMENTS' and DPST= '90040'and item= 'S11024'
A116: =B116&D116 -> 90040S11026 | B116: 90040 | C116: AED - MANUFACTURED UNITS | D116: S11026 | E116: UCW NG FOR ACW | F116: UCW | H116: =IF(LEN(G116)<2,F116,G116) -> UCW | I116: ="update ats_prd_master_new set ProductGroups= "&"'"&H116&"'"&"where ProductGroups="&"'"&F116&"'"&" and DPST= "&"'"&B116&"'"&"and item= "&"'"&D116&"'" -> update ats_prd_master_new set ProductGroups= 'UCW'where ProductGroups='UCW' and DPST= '90040'and item= 'S11026'
A117: =B117&D117 -> 90040S11027 | B117: 90040 | C117: AED - MANUFACTURED UNITS | D117: S11027 | E117: UCW NG FOR TCW | F117: UCW | H117: =IF(LEN(G117)<2,F117,G117) -> UCW | I117: ="update ats_prd_master_new set ProductGroups= "&"'"&H117&"'"&"where ProductGroups="&"'"&F117&"'"&" and DPST= "&"'"&B117&"'"&"and item= "&"'"&D117&"'" -> update ats_prd_master_new set ProductGroups= 'UCW'where ProductGroups='UCW' and DPST= '90040'and item= 'S11027'
A118: =B118&D118 -> 90040S11904 | B118: 90040 | C118: AED - MANUFACTURED UNITS | D118: S11904 | E118: LL 03 022 EP 3HP 350 BASE | F118: WASHING EQUIPMENTS | H118: =IF(LEN(G118)<2,F118,G118) -> WASHING EQUIPMENTS | I118: ="update ats_prd_master_new set ProductGroups= "&"'"&H118&"'"&"where ProductGroups="&"'"&F118&"'"&" and DPST= "&"'"&B118&"'"&"and item= "&"'"&D118&"'" -> update ats_prd_master_new set ProductGroups= 'WASHING EQUIPMENTS'where ProductGroups='WASHING EQUIPMENTS' and DPST= '90040'and item= 'S11904'
A119: =B119&D119 -> 90041120469200 | B119: 90041 | C119: AED - SPARES | D119: 120469200 | E119: DU BUSH 25 ID X 50 L | F119: SPARES / ACCESSORIES | H119: =IF(LEN(G119)<2,F119,G119) -> SPARES / ACCESSORIES | I119: ="update ats_prd_master_new set ProductGroups= "&"'"&H119&"'"&"where ProductGroups="&"'"&F119&"'"&" and DPST= "&"'"&B119&"'"&"and item= "&"'"&D119&"'" -> update ats_prd_master_new set ProductGroups= 'SPARES / ACCESSORIES'where ProductGroups='SPARES / ACCESSORIES' and DPST= '90041'and item= '120469200'
A120: =B120&D120 -> 90041120470510 | B120: 90041 | C120: AED - SPARES | D120: 120470510 | E120: COLUMN SUPPORT PLATE | F120: SPARES / ACCESSORIES | H120: =IF(LEN(G120)<2,F120,G120) -> SPARES / ACCESSORIES | I120: ="update ats_prd_master_new set ProductGroups= "&"'"&H120&"'"&"where ProductGroups="&"'"&F120&"'"&" and DPST= "&"'"&B120&"'"&"and item= "&"'"&D120&"'" -> update ats_prd_master_new set ProductGroups= 'SPARES / ACCESSORIES'where ProductGroups='SPARES / ACCESSORIES' and DPST= '90041'and item= '120470510'
A121: =B121&D121 -> 90040S12001 | B121: 90040 | C121: AED - MANUFACTURED UNITS | D121: S12001 | E121: HS 00 040 4T 1500 9-12 | F121: LIFTING EQUIPMENTS | G121: LIFTING EQUIPMENTS - PU4 | H121: =IF(LEN(G121)<2,F121,G121) -> LIFTING EQUIPMENTS - PU4 | I121: ="update ats_prd_master_new set ProductGroups= "&"'"&H121&"'"&"where ProductGroups="&"'"&F121&"'"&" and DPST= "&"'"&B121&"'"&"and item= "&"'"&D121&"'" -> update ats_prd_master_new set ProductGroups= 'LIFTING EQUIPMENTS - PU4'where ProductGroups='LIFTING EQUIPMENTS' and DPST= '90040'and item= 'S12001'
A122: =B122&D122 -> 90041120470540 | B122: 90041 | C122: AED - SPARES | D122: 120470540 | E122: SPACER PLATE - COLUMN | F122: SPARES / ACCESSORIES | H122: =IF(LEN(G122)<2,F122,G122) -> SPARES / ACCESSORIES | I122: ="update ats_prd_master_new set ProductGroups= "&"'"&H122&"'"&"where ProductGroups="&"'"&F122&"'"&" and DPST= "&"'"&B122&"'"&"and item= "&"'"&D122&"'" -> update ats_prd_master_new set ProductGroups= 'SPARES / ACCESSORIES'where ProductGroups='SPARES / ACCESSORIES' and DPST= '90041'and item= '120470540'
A123: =B123&D123 -> 9004190SA9021PSRF | B123: 90041 | C123: AED - SPARES | D123: 90SA9021PSRF | E123: POWER BOARD FOR 14 | F123: SPARES / ACCESSORIES | H123: =IF(LEN(G123)<2,F123,G123) -> SPARES / ACCESSORIES | I123: ="update ats_prd_master_new set ProductGroups= "&"'"&H123&"'"&"where ProductGroups="&"'"&F123&"'"&" and DPST= "&"'"&B123&"'"&"and item= "&"'"&D123&"'" -> update ats_prd_master_new set ProductGroups= 'SPARES / ACCESSORIES'where ProductGroups='SPARES / ACCESSORIES' and DPST= '90041'and item= '90SA9021PSRF'
A124: =B124&D124 -> 90040S12008 | B124: 90040 | C124: AED - MANUFACTURED UNITS | D124: S12008 | E124: HS 00 080 8T 1525 10-12 | F124: LIFTING EQUIPMENTS | G124: LIFTING EQUIPMENTS - PU4 | H124: =IF(LEN(G124)<2,F124,G124) -> LIFTING EQUIPMENTS - PU4 | I124: ="update ats_prd_master_new set ProductGroups= "&"'"&H124&"'"&"where ProductGroups="&"'"&F124&"'"&" and DPST= "&"'"&B124&"'"&"and item= "&"'"&D124&"'" -> update ats_prd_master_new set ProductGroups= 'LIFTING EQUIPMENTS - PU4'where ProductGroups='LIFTING EQUIPMENTS' and DPST= '90040'and item= 'S12008'
A125: =B125&D125 -> 900429099YA001 | B125: 90042 | C125: AED - TRADED UNITS | D125: 9099YA001 | E125: Collision Repair System 300 | F125: BODY SHOP & PAINT EQUIPMENTS | G125: BODY SHOP & PAINT EQUIPMENTS - CRS | H125: =IF(LEN(G125)<2,F125,G125) -> BODY SHOP & PAINT EQUIPMENTS - CRS | I125: ="update ats_prd_master_new set ProductGroups= "&"'"&H125&"'"&"where ProductGroups="&"'"&F125&"'"&" and DPST= "&"'"&B125&"'"&"and item= "&"'"&D125&"'" -> update ats_prd_master_new set ProductGroups= 'BODY SHOP & PAINT EQUIPMENTS - CRS'where ProductGroups='BODY SHOP & PAINT EQUIPMENTS' and DPST= '90042'and item= '9099YA001'
A126: =B126&D126 -> 900429099YA004 | B126: 90042 | C126: AED - TRADED UNITS | D126: 9099YA004 | E126: Air jack | F126: BODY SHOP & PAINT EQUIPMENTS | G126: BODY SHOP & PAINT EQUIPMENTS - CRS | H126: =IF(LEN(G126)<2,F126,G126) -> BODY SHOP & PAINT EQUIPMENTS - CRS | I126: ="update ats_prd_master_new set ProductGroups= "&"'"&H126&"'"&"where ProductGroups="&"'"&F126&"'"&" and DPST= "&"'"&B126&"'"&"and item= "&"'"&D126&"'" -> update ats_prd_master_new set ProductGroups= 'BODY SHOP & PAINT EQUIPMENTS - CRS'where ProductGroups='BODY SHOP & PAINT EQUIPMENTS' and DPST= '90042'and item= '9099YA004'
A127: =B127&D127 -> 90040S12064 | B127: 90040 | C127: AED - MANUFACTURED UNITS | D127: S12064 | E127: HP 00 040 4T 1500 9-12 W/O FRP | F127: LIFTING EQUIPMENTS | G127: LIFTING EQUIPMENTS - PU4 | H127: =IF(LEN(G127)<2,F127,G127) -> LIFTING EQUIPMENTS - PU4 | I127: ="update ats_prd_master_new set ProductGroups= "&"'"&H127&"'"&"where ProductGroups="&"'"&F127&"'"&" and DPST= "&"'"&B127&"'"&"and item= "&"'"&D127&"'" -> update ats_prd_master_new set ProductGroups= 'LIFTING EQUIPMENTS - PU4'where ProductGroups='LIFTING EQUIPMENTS' and DPST= '90040'and item= 'S12064'
A128: =B128&D128 -> 90041110361810 | B128: 90041 | C128: AED - SPARES | D128: 110361810 | E128: PINION - TCW | F128: SPARES / ACCESSORIES | H128: =IF(LEN(G128)<2,F128,G128) -> SPARES / ACCESSORIES | I128: ="update ats_prd_master_new set ProductGroups= "&"'"&H128&"'"&"where ProductGroups="&"'"&F128&"'"&" and DPST= "&"'"&B128&"'"&"and item= "&"'"&D128&"'" -> update ats_prd_master_new set ProductGroups= 'SPARES / ACCESSORIES'where ProductGroups='SPARES / ACCESSORIES' and DPST= '90041'and item= '110361810'
...

Sheet Sheet2
A1: ColA | B1: DPST | C1: DpstName | D1: Item | E1: Item_desc | F1: ProductGroups | G1: UpdatedDate | H1: Rnk
A2: =B2&D2 -> 900423818010200003YS | B2: 90042 | C2: AED - TRADED UNITS | D2: 3818010200003YS | E2: CENTRAL PROCESSING UNIT FOR 3A | F2: NULL | G2: 43503.191 | H2: 1 | I2: =VLOOKUP(A2,Sheet1!A:G,1,0) -> 900423818010200003YS | J2: =VLOOKUP(A2,Sheet1!A:G,6,0) -> SPARES / ACCESSORIES | K2: ="update ATS_Prd_Master_New set ProductGroups= "&"'"&J2&"'"&"where dpst= "&B2&"and item= "&"'"&D2&"'"&"and ProductGroups is null" -> update ATS_Prd_Master_New set ProductGroups= 'SPARES / ACCESSORIES'where dpst= 90042and item= '3818010200003YS'and ProductGroups is null
A3: =B3&D3 -> 900421199KT002 | B3: 90042 | C3: AED - TRADED UNITS | D3: 1199KT002 | E3: WRP 1250 LITRES/HR | F3: NULL | G3: 43547.191 | H3: 1 | I3: =VLOOKUP(A3,Sheet1!A:G,1,0) -> 900421199KT002 | J3: =VLOOKUP(A3,Sheet1!A:G,6,0) -> ETP/RO/WRP | K3: ="update ATS_Prd_Master_New set ProductGroups= "&"'"&J3&"'"&"where dpst= "&B3&"and item= "&"'"&D3&"'"&"and ProductGroups is null" -> update ATS_Prd_Master_New set ProductGroups= 'ETP/RO/WRP'where dpst= 90042and item= '1199KT002'and ProductGroups is null
A4: =B4&D4 -> 90042S25007 | B4: 90042 | C4: AED - TRADED UNITS | D4: S25007 | E4: ACRU - FA - WITHOUT PRINTER | F4: NULL | G4: 43547.191 | H4: 1 | I4: =VLOOKUP(A4,Sheet1!A:G,1,0) -> 90042S25007 | J4: =VLOOKUP(A4,Sheet1!A:G,6,0) -> AC CHARGING MACHINE | K4: ="update ATS_Prd_Master_New set ProductGroups= "&"'"&J4&"'"&"where dpst= "&B4&"and item= "&"'"&D4&"'"&"and ProductGroups is null" -> update ATS_Prd_Master_New set ProductGroups= 'AC CHARGING MACHINE'where dpst= 90042and item= 'S25007'and ProductGroups is null
A5: =B5&D5 -> 900401699EL007 | B5: 90040 | C5: AED - MANUFACTURED UNITS | D5: 1699EL007 | E5: DOUBLE MOTOR INDUSTRIAL W&D VR | F5: NULL | G5: 43545.192 | H5: 1 | I5: =VLOOKUP(A5,Sheet1!A:G,1,0) -> 900401699EL007 | J5: =VLOOKUP(A5,Sheet1!A:G,6,0) -> WASHING EQUIPMENTS | K5: ="update ATS_Prd_Master_New set ProductGroups= "&"'"&J5&"'"&"where dpst= "&B5&"and item= "&"'"&D5&"'"&"and ProductGroups is null" -> update ATS_Prd_Master_New set ProductGroups= 'WASHING EQUIPMENTS'where dpst= 90040and item= '1699EL007'and ProductGroups is null
A6: =B6&D6 -> 900404899SZ059 | B6: 90040 | C6: AED - MANUFACTURED UNITS | D6: 4899SZ059 | E6: Pull Strap Kit | F6: NULL | G6: 43545.192 | H6: 1 | I6: =VLOOKUP(A6,Sheet1!A:G,1,0) -> 900404899SZ059 | J6: =VLOOKUP(A6,Sheet1!A:G,6,0) -> BODY SHOP & PAINT EQUIPMENTS | K6: ="update ATS_Prd_Master_New set ProductGroups= "&"'"&J6&"'"&"where dpst= "&B6&"and item= "&"'"&D6&"'"&"and ProductGroups is null" -> update ATS_Prd_Master_New set ProductGroups= 'BODY SHOP & PAINT EQUIPMENTS'where dpst= 90040and item= '4899SZ059'and ProductGroups is null
A7: =B7&D7 -> 900404899SZ061 | B7: 90040 | C7: AED - MANUFACTURED UNITS | D7: 4899SZ061 | E7: Pull plier | F7: NULL | G7: 43545.192 | H7: 1 | I7: =VLOOKUP(A7,Sheet1!A:G,1,0) -> 900404899SZ061 | J7: =VLOOKUP(A7,Sheet1!A:G,6,0) -> BODY SHOP & PAINT EQUIPMENTS | K7: ="update ATS_Prd_Master_New set ProductGroups= "&"'"&J7&"'"&"where dpst= "&B7&"and item= "&"'"&D7&"'"&"and ProductGroups is null" -> update ATS_Prd_Master_New set ProductGroups= 'BODY SHOP & PAINT EQUIPMENTS'where dpst= 90040and item= '4899SZ061'and ProductGroups is null
A8: =B8&D8 -> 900404899SZ062 | B8: 90040 | C8: AED - MANUFACTURED UNITS | D8: 4899SZ062 | E8: Chain Shorten 2 Hooks | F8: NULL | G8: 43545.192 | H8: 1 | I8: =VLOOKUP(A8,Sheet1!A:G,1,0) -> 900404899SZ062 | J8: =VLOOKUP(A8,Sheet1!A:G,6,0) -> BODY SHOP & PAINT EQUIPMENTS | K8: ="update ATS_Prd_Master_New set ProductGroups= "&"'"&J8&"'"&"where dpst= "&B8&"and item= "&"'"&D8&"'"&"and ProductGroups is null" -> update ATS_Prd_Master_New set ProductGroups= 'BODY SHOP & PAINT EQUIPMENTS'where dpst= 90040and item= '4899SZ062'and ProductGroups is null
A9: =B9&D9 -> 900404899SZ063 | B9: 90040 | C9: AED - MANUFACTURED UNITS | D9: 4899SZ063 | E9: 1.5 M Chain 10 T with 1 hook | F9: NULL | G9: 43545.192 | H9: 1 | I9: =VLOOKUP(A9,Sheet1!A:G,1,0) -> 900404899SZ063 | J9: =VLOOKUP(A9,Sheet1!A:G,6,0) -> BODY SHOP & PAINT EQUIPMENTS | K9: ="update ATS_Prd_Master_New set ProductGroups= "&"'"&J9&"'"&"where dpst= "&B9&"and item= "&"'"&D9&"'"&"and ProductGroups is null" -> update ATS_Prd_Master_New set ProductGroups= 'BODY SHOP & PAINT EQUIPMENTS'where dpst= 90040and item= '4899SZ063'and ProductGroups is null
A10: =B10&D10 -> 900404899SZ064 | B10: 90040 | C10: AED - MANUFACTURED UNITS | D10: 4899SZ064 | E10: 3 M Chain 10 T with 1 hook | F10: NULL | G10: 43545.192 | H10: 1 | I10: =VLOOKUP(A10,Sheet1!A:G,1,0) -> 900404899SZ064 | J10: =VLOOKUP(A10,Sheet1!A:G,6,0) -> BODY SHOP & PAINT EQUIPMENTS | K10: ="update ATS_Prd_Master_New set ProductGroups= "&"'"&J10&"'"&"where dpst= "&B10&"and item= "&"'"&D10&"'"&"and ProductGroups is null" -> update ATS_Prd_Master_New set ProductGroups= 'BODY SHOP & PAINT EQUIPMENTS'where dpst= 90040and item= '4899SZ064'and ProductGroups is null
A11: =B11&D11 -> 900409099YA001 | B11: 90040 | C11: AED - MANUFACTURED UNITS | D11: 9099YA001 | E11: Collision Repair System 300 | F11: NULL | G11: 43545.192 | H11: 1 | I11: =VLOOKUP(A11,Sheet1!A:G,1,0) -> 900409099YA001 | J11: =VLOOKUP(A11,Sheet1!A:G,6,0) -> BODY SHOP & PAINT EQUIPMENTS | K11: ="update ATS_Prd_Master_New set ProductGroups= "&"'"&J11&"'"&"where dpst= "&B11&"and item= "&"'"&D11&"'"&"and ProductGroups is null" -> update ATS_Prd_Master_New set ProductGroups= 'BODY SHOP & PAINT EQUIPMENTS'where dpst= 90040and item= '9099YA001'and ProductGroups is null
A12: =B12&D12 -> 900409099YA004 | B12: 90040 | C12: AED - MANUFACTURED UNITS | D12: 9099YA004 | E12: Air jack | F12: NULL | G12: 43545.192 | H12: 1 | I12: =VLOOKUP(A12,Sheet1!A:G,1,0) -> 900409099YA004 | J12: =VLOOKUP(A12,Sheet1!A:G,6,0) -> BODY SHOP & PAINT EQUIPMENTS | K12: ="update ATS_Prd_Master_New set ProductGroups= "&"'"&J12&"'"&"where dpst= "&B12&"and item= "&"'"&D12&"'"&"and ProductGroups is null" -> update ATS_Prd_Master_New set ProductGroups= 'BODY SHOP & PAINT EQUIPMENTS'where dpst= 90040and item= '9099YA004'and ProductGroups is null
A13: =B13&D13 -> 900409099YA006 | B13: 90040 | C13: AED - MANUFACTURED UNITS | D13: 9099YA006 | E13: Accessories Kit | F13: NULL | G13: 43545.192 | H13: 1 | I13: =VLOOKUP(A13,Sheet1!A:G,1,0) -> 900409099YA006 | J13: =VLOOKUP(A13,Sheet1!A:G,6,0) -> SPARES / ACCESSORIES | K13: ="update ATS_Prd_Master_New set ProductGroups= "&"'"&J13&"'"&"where dpst= "&B13&"and item= "&"'"&D13&"'"&"and ProductGroups is null" -> update ATS_Prd_Master_New set ProductGroups= 'SPARES / ACCESSORIES'where dpst= 90040and item= '9099YA006'and ProductGroups is null
... A53: =B53&D53 -> 900423999WR027 | B53: 90042 | C53: AED - TRADED UNITS | D53: 3999WR027 | E53: Exhaust Extraction System | F53: NULL | G53: 43540.191 | H53: 1 | I53: =VLOOKUP(A53,Sheet1!A:G,1,0) -> 900423999WR027 | J53: =VLOOKUP(A53,Sheet1!A:G,6,0) -> BODY SHOP & PAINT EQUIPMENTS | K53: ="update ATS_Prd_Master_New set ProductGroups= "&"'"&J53&"'"&"where dpst= "&B53&"and item= "&"'"&D53&"'"&"and ProductGroups is null" -> update ATS_Prd_Master_New set ProductGroups= 'BODY SHOP & PAINT EQUIPMENTS'where dpst= 90042and item= '3999WR027'and ProductGroups is null

Sheet Sheet3
B1: DPST | C1: DpstName | D1: Item | E1: Item_desc | F1: ProductGroups | G1: Lookup
A2: =B2&D2 -> 90041120326630 | B2: 90041 | C2: AED - SPARES | D2: 120326630 | E2: LOCK ASSY RIGHT | F2: SPARES / ACCESSORIES | G2: =VLOOKUP(A2,Sheet2!A:J,1,0) -> #N/A | H2: =VLOOKUP(A2,Sheet2!A:J,6,0) -> #N/A
A3: =B3&D3 -> 90041120353370 | B3: 90041 | C3: AED - SPARES | D3: 120353370 | E3: COVER;TOP;MOTOR | F3: SPARES / ACCESSORIES | G3: =VLOOKUP(A3,Sheet2!A:J,1,0) -> #N/A | H3: =VLOOKUP(A3,Sheet2!A:J,6,0) -> #N/A
A4: =B4&D4 -> 90041120355460 | B4: 90041 | C4: AED - SPARES | D4: 120355460 | E4: TOP PLATE ASSY FOLL POWDER COA | F4: SPARES / ACCESSORIES | G4: =VLOOKUP(A4,Sheet2!A:J,1,0) -> #N/A | H4: =VLOOKUP(A4,Sheet2!A:J,6,0) -> #N/A
A5: =B5&D5 -> 900411203SA1000NU | B5: 90041 | C5: AED - SPARES | D5: 1203SA1000NU | E5: PIN SA1000-WSC | F5: SPARES / ACCESSORIES | G5: =VLOOKUP(A5,Sheet2!A:J,1,0) -> #N/A | H5: =VLOOKUP(A5,Sheet2!A:J,6,0) -> #N/A
A6: =B6&D6 -> 90041120418960 | B6: 90041 | C6: AED - SPARES | D6: 120418960 | E6: HOSE ASSY (3 MTRS) | F6: SPARES / ACCESSORIES | G6: =VLOOKUP(A6,Sheet2!A:J,1,0) -> #N/A | H6: =VLOOKUP(A6,Sheet2!A:J,6,0) -> #N/A
A7: =B7&D7 -> 90041120430551 | B7: 90041 | C7: AED - SPARES | D7: 120430551 | E7: UNION TEE DIA6MM | F7: SPARES / ACCESSORIES | G7: =VLOOKUP(A7,Sheet2!A:J,1,0) -> #N/A | H7: =VLOOKUP(A7,Sheet2!A:J,6,0) -> #N/A
A8: =B8&D8 -> 90041120430552 | B8: 90041 | C8: AED - SPARES | D8: 120430552 | E8: MALE CONNECTOR DIA6X5MM | F8: SPARES / ACCESSORIES | G8: =VLOOKUP(A8,Sheet2!A:J,1,0) -> #N/A | H8: =VLOOKUP(A8,Sheet2!A:J,6,0) -> #N/A
A9: =B9&D9 -> 90041120452510 | B9: 90041 | C9: AED - SPARES | D9: 120452510 | E9: COVER HOLDER; PIN - 3TON | F9: SPARES / ACCESSORIES | G9: =VLOOKUP(A9,Sheet2!A:J,1,0) -> #N/A | H9: =VLOOKUP(A9,Sheet2!A:J,6,0) -> #N/A
A10: =B10&D10 -> 90041120453550 | B10: 90041 | C10: AED - SPARES | D10: 120453550 | E10: PULLEY MOTOR M/C SAL | F10: SPARES / ACCESSORIES | G10: =VLOOKUP(A10,Sheet2!A:J,1,0) -> #N/A | H10: =VLOOKUP(A10,Sheet2!A:J,6,0) -> #N/A
A11: =B11&D11 -> 90041120454600 | B11: 90041 | C11: AED - SPARES | D11: 120454600 | E11: STUD ASSY,ARM - SAL HYN | F11: SPARES / ACCESSORIES | G11: =VLOOKUP(A11,Sheet2!A:J,1,0) -> #N/A | H11: =VLOOKUP(A11,Sheet2!A:J,6,0) -> #N/A
A12: =B12&D12 -> 90041120463570 | B12: 90041 | C12: AED - SPARES | D12: 120463570 | E12: PIN (CYLINDER BOTTOM) | F12: SPARES / ACCESSORIES | G12: =VLOOKUP(A12,Sheet2!A:J,1,0) -> #N/A | H12: =VLOOKUP(A12,Sheet2!A:J,6,0) -> #N/A
A13: =B13&D13 -> 90041120463850 | B13: 90041 | C13: AED - SPARES | D13: 120463850 | E13: BREATHER | F13: SPARES / ACCESSORIES | G13: =VLOOKUP(A13,Sheet2!A:J,1,0) -> #N/A | H13: =VLOOKUP(A13,Sheet2!A:J,6,0) -> #N/A
... A23: =B23&D23 -> 90029SCIN0005 | B23: 90029 | C23: Rocd-service revenue | D23: SCIN0005 | E23: AMC CHARGES | F23: SERVICE BILLING | G23: =VLOOKUP(A23,Sheet2!A:J,1,0) -> #N/A | H23: =VLOOKUP(A23,Sheet2!A:J,6,0) -> #N/A
A24: =B24&D24 -> 90029SCIN0006 | B24: 90029 | C24: Rocd-service revenue | D24: SCIN0006 | F24: SERVICE BILLING | G24: =VLOOKUP(A24,Sheet2!A:J,1,0) -> #N/A | H24: =VLOOKUP(A24,Sheet2!A:J,6,0) -> #N/A
A25: =B25&D25 -> 90029SCIN0007 | B25: 90029 | C25: Rocd-service revenue | D25: SCIN0007 | F25: SERVICE BILLING | G25: =VLOOKUP(A25,Sheet2!A:J,1,0) -> #N/A | H25: =VLOOKUP(A25,Sheet2!A:J,6,0) -> #N/A
A26: =B26&D26 -> 90029SCIN0008 | B26: 90029 | C26: Rocd-service revenue | D26: SCIN0008 | F26: SERVICE BILLING | G26: =VLOOKUP(A26,Sheet2!A:J,1,0) -> #N/A | H26: =VLOOKUP(A26,Sheet2!A:J,6,0) -> #N/A
A27: =B27&D27 -> 90029SCIN0009 | B27: 90029 | C27: Rocd-service revenue | D27: SCIN0009 | F27: SERVICE BILLING | G27: =VLOOKUP(A27,Sheet2!A:J,1,0) -> #N/A | H27: =VLOOKUP(A27,Sheet2!A:J,6,0) -> #N/A
A28: =B28&D28 -> 90040008400130 | B28: 90040 | C28: AED - MANUFACTURED UNITS | D28: 008400130 | E28: ON DELAY TIMER | F28: SPARES / ACCESSORIES | G28: =VLOOKUP(A28,Sheet2!A:J,1,0) -> #N/A | H28: =VLOOKUP(A28,Sheet2!A:J,6,0) -> #N/A
A29: =B29&D29 -> 90040008937011 | B29: 90040 | C29: AED - MANUFACTURED UNITS | D29: 008937011 | E29: TRANSFORMER 50VA 415V-0-24V. | F29: SPARES / ACCESSORIES | G29: =VLOOKUP(A29,Sheet2!A:J,1,0) -> #N/A | H29: =VLOOKUP(A29,Sheet2!A:J,6,0) -> #N/A
A30: =B30&D30 -> 90040080302630 | B30: 90040 | C30: AED - MANUFACTURED UNITS | D30: 080302630 | E30: CUSHION CHAIR | F30: MOBILE SERVICE UNITS | G30: =VLOOKUP(A30,Sheet2!A:J,1,0) -> #N/A | H30: =VLOOKUP(A30,Sheet2!A:J,6,0) -> #N/A
A31: =B31&D31 -> 90040080302730 | B31: 90040 | C31: AED - MANUFACTURED UNITS | D31: 080302730 | E31: AIR TANK ASSY | F31: MOBILE SERVICE UNITS | G31: =VLOOKUP(A31,Sheet2!A:J,1,0) -> #N/A | H31: =VLOOKUP(A31,Sheet2!A:J,6,0) -> #N/A
A32: =B32&D32 -> 90041130315300 | B32: 90041 | C32: AED - SPARES | D32: 130315300 | E32: COVER ASSY GREASE DRUM | F32: SPARES / ACCESSORIES | G32: =VLOOKUP(A32,Sheet2!A:J,1,0) -> #N/A | H32: =VLOOKUP(A32,Sheet2!A:J,6,0) -> #N/A
A33: =B33&D33 -> 90041130416931 | B33: 90041 | C33: AED - SPARES | D33: 130416931 | E33: DRUM ASSY GREASE | F33: SPARES / ACCESSORIES | G33: =VLOOKUP(A33,Sheet2!A:J,1,0) -> #N/A | H33: =VLOOKUP(A33,Sheet2!A:J,6,0) -> #N/A
A34: =B34&D34 -> 90040080302750 | B34: 90040 | C34: AED - MANUFACTURED UNITS | D34: 080302750 | E34: COMPRESSOR ASSY | F34: MMS | G34: =VLOOKUP(A34,Sheet2!A:J,1,0) -> #N/A | H34: =VLOOKUP(A34,Sheet2!A:J,6,0) -> #N/A
A35: =B35&D35 -> 90041130453220 | B35: 90041 | C35: AED - SPARES | D35: 130453220 | E35: ADAPTER BUNG M/C | F35: SPARES / ACCESSORIES | G35: =VLOOKUP(A35,Sheet2!A:J,1,0) -> #N/A | H35: =VLOOKUP(A35,Sheet2!A:J,6,0) -> #N/A
A36: =B36&D36 -> 90041130493020 | B36: 90041 | C36: AED - SPARES | D36: 130493020 | E36: PUMP WITH GUN ASSY-5 KG | F36: SPARES / ACCESSORIES | G36: =VLOOKUP(A36,Sheet2!A:J,1,0) -> #N/A | H36: =VLOOKUP(A36,Sheet2!A:J,6,0) -> #N/A
A37: =B37&D37 -> 90040080302820 | B37: 90040 | C37: AED - MANUFACTURED UNITS | D37: 080302820 | E37: WATER TANK ASSY | F37: MMS | G37: =VLOOKUP(A37,Sheet2!A:J,1,0) -> #N/A | H37: =VLOOKUP(A37,Sheet2!A:J,6,0) -> #N/A
A38: =B38&D38 -> 900411332HC0801PI | B38: 90041 | C38: AED - SPARES | D38: 1332HC0801PI | E38: WIND NOZZLE | F38: SPARES / ACCESSORIES | G38: =VLOOKUP(A38,Sheet2!A:J,1,0) -> #N/A | H38: =VLOOKUP(A38,Sheet2!A:J,6,0) -> #N/A
A39: =B39&D39 -> 900411332HC0803PI | B39: 90041 | C39: AED - SPARES | D39: 1332HC0803PI | E39: MINI BALL VALVE | F39: SPARES / ACCESSORIES | G39: =VLOOKUP(A39,Sheet2!A:J,1,0) -> #N/A | H39: =VLOOKUP(A39,Sheet2!A:J,6,0) -> #N/A
... A202: =B202&D202 -> 9004150TP02007MT | B202: 90041 | C202: AED - SPARES | D202: 50TP02007MT | E202: ROLLER ASSEMBLY | F202: SPARES / ACCESSORIES | G202: =VLOOKUP(A202,Sheet2!A:J,1,0) -> #N/A | H202: =VLOOKUP(A202,Sheet2!A:J,6,0) -> #N/A
A203: =B203&D203 -> 900423818010200003YS | B203: 90042 | C203: AED - TRADED UNITS | D203: 3818010200003YS | E203: CENTRAL PROCESSING UNIT FOR 3A | F203: SPARES / ACCESSORIES | G203: =VLOOKUP(A203,Sheet2!A:J,1,0) -> 900423818010200003YS | H203: =VLOOKUP(A203,Sheet2!A:J,10,0) -> SPARES / ACCESSORIES | I203: =IF(F203=H203,TRUE,FALSE) -> TRUE
A204: =B204&D204 -> 90040S19002 | B204: 90040 | C204: AED - MANUFACTURED UNITS | D204: S19002 | E204: SPARK PLUG CLEANER UNIT | F204: TYRE INFLATORS | G204: =VLOOKUP(A204,Sheet2!A:J,1,0) -> #N/A | H204: =VLOOKUP(A204,Sheet2!A:J,6,0) -> #N/A
A205: =B205&D205 -> 90040S23004 | B205: 90040 | C205: AED - MANUFACTURED UNITS | D205: S23004 | E205: VWB ASSEMBLY | F205: WHEEL SERVICE EQUIPMENTS | G205: =VLOOKUP(A205,Sheet2!A:J,1,0) -> #N/A | H205: =VLOOKUP(A205,Sheet2!A:J,6,0) -> #N/A
A206: =B206&D206 -> 90040S25004 | B206: 90040 | C206: AED - MANUFACTURED UNITS | D206: S25004 | E206: AC RECOVERY UNIT | F206: AC CHARGING MACHINE | G206: =VLOOKUP(A206,Sheet2!A:J,1,0) -> #N/A | H206: =VLOOKUP(A206,Sheet2!A:J,6,0) -> #N/A
A207: =B207&D207 -> 90049120459360 | B207: 90049 | C207: SUPPLIER SALES | D207: 120459360 | E207: CYLINDER SEAL KIT FOR 63DIA | F207: SUPPLIER SALES | G207: =VLOOKUP(A207,Sheet2!A:J,1,0) -> #N/A | H207: =VLOOKUP(A207,Sheet2!A:J,6,0) -> #N/A
A208: =B208&D208 -> 90049123465960 | B208: 90049 | C208: SUPPLIER SALES | D208: 123465960 | E208: SEAL KIT CYLINDER DH FPL | F208: SUPPLIER SALES | G208: =VLOOKUP(A208,Sheet2!A:J,1,0) -> #N/A | H208: =VLOOKUP(A208,Sheet2!A:J,6,0) -> #N/A
A209: =B209&D209 -> 90040S25005 | B209: 90040 | C209: AED - MANUFACTURED UNITS | D209: S25005 | E209: AC RECOVERY - FULLY AUTOMATIC | F209: AC CHARGING MACHINE | G209: =VLOOKUP(A209,Sheet2!A:J,1,0) -> #N/A | H209: =VLOOKUP(A209,Sheet2!A:J,6,0) -> #N/A
A210: =B210&D210 -> 90049460349920 | B210: 90049 | C210: SUPPLIER SALES | D210: 460349920 | E210: EXTRACTOR ASSY M1-C2 | F210: SUPPLIER SALES | G210: =VLOOKUP(A210,Sheet2!A:J,1,0) -> #N/A | H210: =VLOOKUP(A210,Sheet2!A:J,6,0) -> #N/A
A211: =B211&D211 -> 90049460349940 | B211: 90049 | C211: SUPPLIER SALES | D211: 460349940 | E211: EX BLOWER BOX ASSY | F211: SUPPLIER SALES | G211: =VLOOKUP(A211,Sheet2!A:J,1,0) -> #N/A | H211: =VLOOKUP(A211,Sheet2!A:J,6,0) -> #N/A
A212: =B212&D212 -> 90040S25007 | B212: 90040 | C212: AED - MANUFACTURED UNITS | D212: S25007 | E212: ACRU - FA - WITHOUT PRINTER | F212: AC CHARGING MACHINE | G212: =VLOOKUP(A212,Sheet2!A:J,1,0) -> #N/A | H212: =VLOOKUP(A212,Sheet2!A:J,6,0) -> #N/A
A213: =B213&D213 -> 90040S38006 | B213: 90040 | C213: AED - MANUFACTURED UNITS | D213: S38006 | E213: NEW GEN RF 2D WHEEL ALIGNER | F213: WHEEL SERVICE EQUIPMENTS | G213: =VLOOKUP(A213,Sheet2!A:J,1,0) -> #N/A | H213: =VLOOKUP(A213,Sheet2!A:J,6,0) -> #N/A
A214: =B214&D214 -> 90040S38007 | B214: 90040 | C214: AED - MANUFACTURED UNITS | D214: S38007 | E214: 3D - WHEEL ALIGNER | F214: WHEEL SERVICE EQUIPMENTS | G214: =VLOOKUP(A214,Sheet2!A:J,1,0) -> #N/A | H214: =VLOOKUP(A214,Sheet2!A:J,6,0) -> #N/A
A215: =B215&D215 -> 90040S38010 | B215: 90040 | C215: AED - MANUFACTURED UNITS | D215: S38010 | E215: 3D WHEEL ALIGNER | F215: WHEEL SERVICE EQUIPMENTS | G215: =VLOOKUP(A215,Sheet2!A:J,1,0) -> #N/A | H215: =VLOOKUP(A215,Sheet2!A:J,6,0) -> #N/A
... A954: =B954&D954 -> 90041110457840 | B954: 90041 | C954: AED - SPARES | D954: 110457840 | E954: LOCKING PLATE | F954: SPARES / ACCESSORIES | G954: =VLOOKUP(A954,Sheet2!A:J,1,0) -> #N/A | H954: =VLOOKUP(A954,Sheet2!A:J,6,0) -> #N/A
A955: =B955&D955 -> 900421199KT002 | B955: 90042 | C955: AED - TRADED UNITS | D955: 1199KT002 | E955: WRP 1250 LITRES/HR | F955: SPARES / ACCESSORIES | G955: =VLOOKUP(A955,Sheet2!A:J,1,0) -> 900421199KT002 | H955: =VLOOKUP(A955,Sheet2!A:J,10,0) -> ETP/RO/WRP | I955: =IF(F955=H955,TRUE,FALSE) -> FALSE
A956: =B956&D956 -> 90042S25007 | B956: 90042 | C956: AED - TRADED UNITS | D956: S25007 | E956: ACRU - FA - WITHOUT PRINTER | F956: AC CHARGING MACHINE | G956: =VLOOKUP(A956,Sheet2!A:J,1,0) -> 90042S25007 | H956: =VLOOKUP(A956,Sheet2!A:J,10,0) -> AC CHARGING MACHINE | I956: =IF(F956=H956,TRUE,FALSE) -> TRUE
A957: =B957&D957 -> 90041110457850 | B957: 90041 | C957: AED - SPARES | D957: 110457850 | E957: FILTER REGULATOR 162719 | F957: SPARES / ACCESSORIES | G957: =VLOOKUP(A957,Sheet2!A:J,1,0) -> #N/A | H957: =VLOOKUP(A957,Sheet2!A:J,6,0) -> #N/A
A958: =B958&D958 -> 90041110457890 | B958: 90041 | C958: AED - SPARES | D958: 110457890 | E958: PRESSURE SWITCH 161760 | F958: SPARES / ACCESSORIES | G958: =VLOOKUP(A958,Sheet2!A:J,1,0) -> #N/A | H958: =VLOOKUP(A958,Sheet2!A:J,6,0) -> #N/A
A959: =B959&D959 -> 90049080402220 | B959: 90049 | C959: SUPPLIER SALES | D959: 080402220 | E959: OIL HOSE ASSY 1/2 M X 650 MM | F959: SUPPLIER SALES | G959: =VLOOKUP(A959,Sheet2!A:J,1,0) -> #N/A | H959: =VLOOKUP(A959,Sheet2!A:J,6,0) -> #N/A
A960: =B960&D960 -> 900491399PI001 | B960: 90049 | C960: SUPPLIER SALES | D960: 1399PI001 | E960: WASTE OIL COLLECTION TROLLEY | F960: SUPPLIER SALES | G960: =VLOOKUP(A960,Sheet2!A:J,1,0) -> #N/A | H960: =VLOOKUP(A960,Sheet2!A:J,6,0) -> #N/A
A961: =B961&D961 -> 90041110457910 | B961: 90041 | C961: AED - SPARES | D961: 110457910 | E961: PRECISION PR REGULATOR 159501 | F961: SPARES / ACCESSORIES | G961: =VLOOKUP(A961,Sheet2!A:J,1,0) -> #N/A | H961: =VLOOKUP(A961,Sheet2!A:J,6,0) -> #N/A
A962: =B962&D962 -> 90041110457920 | B962: 90041 | C962: AED - SPARES | D962: 110457920 | E962: NRV 153450 HA 1/4 QS-6 | F962: SPARES / ACCESSORIES | G962: =VLOOKUP(A962,Sheet2!A:J,1,0) -> #N/A | H962: =VLOOKUP(A962,Sheet2!A:J,6,0) -> #N/A
A963: =B963&D963 -> 90041110457960 | B963: 90041 | C963: AED - SPARES | D963: 110457960 | E963: DCV 6211 MFH-5-1/4 | F963: SPARES / ACCESSORIES | G963: =VLOOKUP(A963,Sheet2!A:J,1,0) -> #N/A | H963: =VLOOKUP(A963,Sheet2!A:J,6,0) -> #N/A
A964: =B964&D964 -> 90041110457970 | B964: 90041 | C964: AED - SPARES | D964: 110457970 | E964: SOLENOID COIL 4527 MSFG 24/42- | F964: SPARES / ACCESSORIES | G964: =VLOOKUP(A964,Sheet2!A:J,1,0) -> #N/A | H964: =VLOOKUP(A964,Sheet2!A:J,6,0) -> #N/A
A965: =B965&D965 -> 90041110458020 | B965: 90041 | C965: AED - SPARES | D965: 110458020 | E965: SILENCER 534220 UC-1/4-20 | F965: SPARES / ACCESSORIES | G965: =VLOOKUP(A965,Sheet2!A:J,1,0) -> #N/A | H965: =VLOOKUP(A965,Sheet2!A:J,6,0) -> #N/A
A966: =B966&D966 -> 90041110458070 | B966: 90041 | C966: AED - SPARES | D966: 110458070 | E966: PUSH IN ELBOW 153047 QSL G1/4 | F966: SPARES / ACCESSORIES | G966: =VLOOKUP(A966,Sheet2!A:J,1,0) -> #N/A | H966: =VLOOKUP(A966,Sheet2!A:J,6,0) -> #N/A
A967: =B967&D967 -> 90041110458080 | B967: 90041 | C967: AED - SPARES | D967: 110458080 | E967: MULTIPLE DISTRIBUTOR 153223 QS | F967: SPARES / ACCESSORIES | G967: =VLOOKUP(A967,Sheet2!A:J,1,0) -> #N/A | H967: =VLOOKUP(A967,Sheet2!A:J,6,0) -> #N/A
A968: =B968&D968 -> 90041110458090 | B968: 90041 | C968: AED - SPARES | D968: 110458090 | E968: ROLLER BRUSH AND BLOWER MVT | F968: SPARES / ACCESSORIES | G968: =VLOOKUP(A968,Sheet2!A:J,1,0) -> #N/A | H968: =VLOOKUP(A968,Sheet2!A:J,6,0) -> #N/A
... A1842: =B1842&D1842 -> 90041118300150 | B1842: 90041 | C1842: AED - SPARES | D1842: 118300150 | E1842: 4C*1.0SQ.MM DRAGCHAINDUTYCABLE | F1842: SPARES / ACCESSORIES | G1842: =VLOOKUP(A1842,Sheet2!A:J,1,0) -> #N/A | H1842: =VLOOKUP(A1842,Sheet2!A:J,6,0) -> #N/A
A1843: =B1843&D1843 -> 900401699EL007 | B1843: 90040 | C1843: AED - MANUFACTURED UNITS | D1843: 1699EL007 | E1843: DOUBLE MOTOR INDUSTRIAL W&D VR | F1843: WASHING EQUIPMENTS | G1843: =VLOOKUP(A1843,Sheet2!A:J,1,0) -> 900401699EL007 | H1843: =VLOOKUP(A1843,Sheet2!A:J,10,0) -> WASHING EQUIPMENTS | I1843: =IF(F1843=H1843,TRUE,FALSE) -> TRUE
A1844: =B1844&D1844 -> 90041118300160 | B1844: 90041 | C1844: AED - SPARES | D1844: 118300160 | E1844: 4C*1.0SQ.MM DRAGCHAINDUTYCABLE | F1844: SPARES / ACCESSORIES | G1844: =VLOOKUP(A1844,Sheet2!A:J,1,0) -> #N/A | H1844: =VLOOKUP(A1844,Sheet2!A:J,6,0) -> #N/A
A1845: =B1845&D1845 -> 900404899SZ059 | B1845: 90040 | C1845: AED - MANUFACTURED UNITS | D1845: 4899SZ059 | E1845: Pull Strap Kit | F1845: BODY SHOP & PAINT EQUIPMENTS | G1845: =VLOOKUP(A1845,Sheet2!A:J,1,0) -> 900404899SZ059 | H1845: =VLOOKUP(A1845,Sheet2!A:J,10,0) -> BODY SHOP & PAINT EQUIPMENTS | I1845: =IF(F1845=H1845,TRUE,FALSE) -> TRUE
A1846: =B1846&D1846 -> 90041118300200 | B1846: 90041 | C1846: AED - SPARES | D1846: 118300200 | E1846: ELECTRICAL CNTRL PNL FOR NG UC | F1846: SPARES / ACCESSORIES | G1846: =VLOOKUP(A1846,Sheet2!A:J,1,0) -> #N/A | H1846: =VLOOKUP(A1846,Sheet2!A:J,6,0) -> #N/A
A1847: =B1847&D1847 -> 90041118300260 | B1847: 90041 | C1847: AED - SPARES | D1847: 118300260 | E1847: ELECTRICAL CONTROL PANEL BOX 6 | F1847: SPARES / ACCESSORIES | G1847: =VLOOKUP(A1847,Sheet2!A:J,1,0) -> #N/A | H1847: =VLOOKUP(A1847,Sheet2!A:J,6,0) -> #N/A
A1848: =B1848&D1848 -> 90041118300270 | B1848: 90041 | C1848: AED - SPARES | D1848: 118300270 | E1848: ELECTRICAL CONTROL PANEL BOX 3 | F1848: SPARES / ACCESSORIES | G1848: =VLOOKUP(A1848,Sheet2!A:J,1,0) -> #N/A | H1848: =VLOOKUP(A1848,Sheet2!A:J,6,0) -> #N/A
A1849: =B1849&D1849 -> 90041118300370 | B1849: 90041 | C1849: AED - SPARES | D1849: 118300370 | E1849: UCW STANDALONE PANEL BOX | F1849: SPARES / ACCESSORIES | G1849: =VLOOKUP(A1849,Sheet2!A:J,1,0) -> #N/A | H1849: =VLOOKUP(A1849,Sheet2!A:J,6,0) -> #N/A
A1850: =B1850&D1850 -> 90041118300430 | B1850: 90041 | C1850: AED - SPARES | D1850: 118300430 | E1850: TCW- UCW CABLE 16X0.75SQ.MM | F1850: SPARES / ACCESSORIES | G1850: =VLOOKUP(A1850,Sheet2!A:J,1,0) -> #N/A | H1850: =VLOOKUP(A1850,Sheet2!A:J,6,0) -> #N/A
A1851: =B1851&D1851 -> 90041118400019 | B1851: 90041 | C1851: AED - SPARES | D1851: 118400019 | E1851: ULTRASONIC SENSOR 0.3TO 3.5MTR | F1851: SPARES / ACCESSORIES | G1851: =VLOOKUP(A1851,Sheet2!A:J,1,0) -> #N/A | H1851: =VLOOKUP(A1851,Sheet2!A:J,6,0) -> #N/A
A1852: =B1852&D1852 -> 900404899SZ061 | B1852: 90040 | C1852: AED - MANUFACTURED UNITS | D1852: 4899SZ061 | E1852: Pull plier | F1852: BODY SHOP & PAINT EQUIPMENTS | G1852: =VLOOKUP(A1852,Sheet2!A:J,1,0) -> 900404899SZ061 | H1852: =VLOOKUP(A1852,Sheet2!A:J,10,0) -> BODY SHOP & PAINT EQUIPMENTS | I1852: =IF(F1852=H1852,TRUE,FALSE) -> TRUE
A1853: =B1853&D1853 -> 900404899SZ062 | B1853: 90040 | C1853: AED - MANUFACTURED UNITS | D1853: 4899SZ062 | E1853: Chain Shorten 2 Hooks | F1853: BODY SHOP & PAINT EQUIPMENTS | G1853: =VLOOKUP(A1853,Sheet2!A:J,1,0) -> 900404899SZ062 | H1853: =VLOOKUP(A1853,Sheet2!A:J,10,0) -> BODY SHOP & PAINT EQUIPMENTS | I1853: =IF(F1853=H1853,TRUE,FALSE) -> TRUE
A1854: =B1854&D1854 -> 90041118400039 | B1854: 90041 | C1854: AED - SPARES | D1854: 118400039 | E1854: 9A,24V DC CONTACTOR WITH 1NC | F1854: SPARES / ACCESSORIES | G1854: =VLOOKUP(A1854,Sheet2!A:J,1,0) -> #N/A | H1854: =VLOOKUP(A1854,Sheet2!A:J,6,0) -> #N/A
A1855: =B1855&D1855 -> 90041118400040 | B1855: 90041 | C1855: AED - SPARES | D1855: 118400040 | E1855: CONTACTOR - 9A | F1855: SPARES / ACCESSORIES | G1855: =VLOOKUP(A1855,Sheet2!A:J,1,0) -> #N/A | H1855: =VLOOKUP(A1855,Sheet2!A:J,6,0) -> #N/A
A1856: =B1856&D1856 -> 900404899SZ063 | B1856: 90040 | C1856: AED - MANUFACTURED UNITS | D1856: 4899SZ063 | E1856: 1.5 M Chain 10 T with 1 hook | F1856: BODY SHOP & PAINT EQUIPMENTS | G1856: =VLOOKUP(A1856,Sheet2!A:J,1,0) -> 900404899SZ063 | H1856: =VLOOKUP(A1856,Sheet2!A:J,10,0) -> BODY SHOP & PAINT EQUIPMENTS | I1856: =IF(F1856=H1856,TRUE,FALSE) -> TRUE
A1857: =B1857&D1857 -> 900404899SZ064 | B1857: 90040 | C1857: AED - MANUFACTURED UNITS | D1857: 4899SZ064 | E1857: 3 M Chain 10 T with 1 hook | F1857: BODY SHOP & PAINT EQUIPMENTS | G1857: =VLOOKUP(A1857,Sheet2!A:J,1,0) -> 900404899SZ064 | H1857: =VLOOKUP(A1857,Sheet2!A:J,10,0) -> BODY SHOP & PAINT EQUIPMENTS | I1857: =IF(F1857=H1857,TRUE,FALSE) -> TRUE
A1858: =B1858&D1858 -> 90041118400050 | B1858: 90041 | C1858: AED - SPARES | D1858: 118400050 | E1858: RELAYS 24V DC COIL | F1858: SPARES / ACCESSORIES | G1858: =VLOOKUP(A1858,Sheet2!A:J,1,0) -> #N/A | H1858: =VLOOKUP(A1858,Sheet2!A:J,6,0) -> #N/A
A1859: =B1859&D1859 -> 900409099YA001 | B1859: 90040 | C1859: AED - MANUFACTURED UNITS | D1859: 9099YA001 | E1859: Collision Repair System 300 | F1859: BODY SHOP & PAINT EQUIPMENTS | G1859: =VLOOKUP(A1859,Sheet2!A:J,1,0) -> 900409099YA001 | H1859: =VLOOKUP(A1859,Sheet2!A:J,10,0) -> BODY SHOP & PAINT EQUIPMENTS | I1859: =IF(F1859=H1859,TRUE,FALSE) -> TRUE
A1860: =B1860&D1860 -> 900409099YA004 | B1860: 90040 | C1860: AED - MANUFACTURED UNITS | D1860: 9099YA004 | E1860: Air jack | F1860: BODY SHOP & PAINT EQUIPMENTS | G1860: =VLOOKUP(A1860,Sheet2!A:J,1,0) -> 900409099YA004 | H1860: =VLOOKUP(A1860,Sheet2!A:J,10,0) -> BODY SHOP & PAINT EQUIPMENTS | I1860: =IF(F1860=H1860,TRUE,FALSE) -> TRUE
A1861: =B1861&D1861 -> 90041118400080 | B1861: 90041 | C1861: AED - SPARES | D1861: 118400080 | E1861: MICRO DRIVE VLT FC51 | F1861: SPARES / ACCESSORIES | G1861: =VLOOKUP(A1861,Sheet2!A:J,1,0) -> #N/A | H1861: =VLOOKUP(A1861,Sheet2!A:J,6,0) -> #N/A
A1862: =B1862&D1862 -> 900409099YA006 | B1862: 90040 | C1862: AED - MANUFACTURED UNITS | D1862: 9099YA006 | E1862: Accessories Kit | F1862: SPARES / ACCESSORIES | G1862: =VLOOKUP(A1862,Sheet2!A:J,1,0) -> 900409099YA006 | H1862: =VLOOKUP(A1862,Sheet2!A:J,10,0) -> SPARES / ACCESSORIES | I1862: =IF(F1862=H1862,TRUE,FALSE) -> TRUE
A1863: =B1863&D1863 -> 900412305PR40876CE | B1863: 90041 | C1863: AED - SPARES | D1863: 2305PR40876CE | E1863: PANEL COMPLT WITH SWITCH BOARD | F1863: SPARES / ACCESSORIES | G1863: =VLOOKUP(A1863,Sheet2!A:J,1,0) -> #N/A | H1863: =VLOOKUP(A1863,Sheet2!A:J,6,0) -> #N/A
A1864: =B1864&D1864 -> 90041118400100 | B1864: 90041 | C1864: AED - SPARES | D1864: 118400100 | E1864: OVERLOAD RELAY 7-10A | F1864: SPARES / ACCESSORIES | G1864: =VLOOKUP(A1864,Sheet2!A:J,1,0) -> #N/A | H1864: =VLOOKUP(A1864,Sheet2!A:J,6,0) -> #N/A
A1865: =B1865&D1865 -> 90041MCS0000316 | B1865: 90041 | C1865: AED - SPARES | D1865: MCS0000316 | E1865: DRI BRITE S3280005 | F1865: SPARES / ACCESSORIES | G1865: =VLOOKUP(A1865,Sheet2!A:J,1,0) -> #N/A | H1865: =VLOOKUP(A1865,Sheet2!A:J,6,0) -> #N/A
A1866: =B1866&D1866 -> 90041118400130 | B1866: 90041 | C1866: AED - SPARES | D1866: 118400130 | E1866: OVERLOAD RELAY 1.4-2A | F1866: SPARES / ACCESSORIES | G1866: =VLOOKUP(A1866,Sheet2!A:J,1,0) -> #N/A | H1866: =VLOOKUP(A1866,Sheet2!A:J,6,0) -> #N/A
A1867: =B1867&D1867 -> 900513604DIP40 | B1867: 90051 | C1867: PNEUMATIC TOOLS SPARES | D1867: 3604DIP40 | E1867: BUSH VALVE REVERSE 1525 | F1867: SPARES / ACCESSORIES | G1867: =VLOOKUP(A1867,Sheet2!A:J,1,0) -> #N/A | H1867: =VLOOKUP(A1867,Sheet2!A:J,6,0) -> #N/A
A1868: =B1868&D1868 -> 90041118400180 | B1868: 90041 | C1868: AED - SPARES | D1868: 118400180 | E1868: PRESSURE SWITCH KPI 35 | F1868: SPARES / ACCESSORIES | G1868: =VLOOKUP(A1868,Sheet2!A:J,1,0) -> #N/A | H1868: =VLOOKUP(A1868,Sheet2!A:J,6,0) -> #N/A
A1869: =B1869&D1869 -> 90051MCS0000778 | B1869: 90051 | C1869: PNEUMATIC TOOLS SPARES | D1869: MCS0000778 | E1869: ELGI HOIST LUBE 185 LITRES | F1869: SPARES / ACCESSORIES | G1869: =VLOOKUP(A1869,Sheet2!A:J,1,0) -> #N/A | H1869: =VLOOKUP(A1869,Sheet2!A:J,6,0) -> #N/A
A1870: =B1870&D1870 -> 90041118400200 | B1870: 90041 | C1870: AED - SPARES | D1870: 118400200 | E1870: Proximity Switch 12 Dia | F1870: SPARES / ACCESSORIES | G1870: =VLOOKUP(A1870,Sheet2!A:J,1,0) -> #N/A | H1870: =VLOOKUP(A1870,Sheet2!A:J,6,0) -> #N/A
A1871: =B1871&D1871 -> 90041118400210 | B1871: 90041 | C1871: AED - SPARES | D1871: 118400210 | E1871: PROXIMITY SWITCH 18 DIA | F1871: SPARES / ACCESSORIES | G1871: =VLOOKUP(A1871,Sheet2!A:J,1,0) -> #N/A | H1871: =VLOOKUP(A1871,Sheet2!A:J,6,0) -> #N/A
A1872: =B1872&D1872 -> 90041118400220 | B1872: 90041 | C1872: AED - SPARES | D1872: 118400220 | E1872: PHOTO SENSOR - 15M - CYL | F1872: SPARES / ACCESSORIES | G1872: =VLOOKUP(A1872,Sheet2!A:J,1,0) -> #N/A | H1872: =VLOOKUP(A1872,Sheet2!A:J,6,0) -> #N/A
A1873: =B1873&D1873 -> 90041118400240 | B1873: 90041 | C1873: AED - SPARES | D1873: 118400240 | E1873: IO MODULE | F1873: SPARES / ACCESSORIES | G1873: =VLOOKUP(A1873,Sheet2!A:J,1,0) -> #N/A | H1873: =VLOOKUP(A1873,Sheet2!A:J,6,0) -> #N/A
A1874: =B1874&D1874 -> 90041118400250 | B1874: 90041 | C1874: AED - SPARES | D1874: 118400250 | E1874: VOLTAGE MONITERING RELAYABB | F1874: SPARES / ACCESSORIES | G1874: =VLOOKUP(A1874,Sheet2!A:J,1,0) -> #N/A | H1874: =VLOOKUP(A1874,Sheet2!A:J,6,0) -> #N/A
... A2038: =B2038&D2038 -> 90041120354560 | B2038: 90041 | C2038: AED - SPARES | D2038: 120354560 | E2038: CARRIAGE FOLLOWER ASSY | F2038: SPARES / ACCESSORIES | G2038: =VLOOKUP(A2038,Sheet2!A:J,1,0) -> #N/A | H2038: =VLOOKUP(A2038,Sheet2!A:J,6,0) -> #N/A
A2039: =B2039&D2039 -> 90040Z08094 | B2039: 90040 | C2039: AED - MANUFACTURED UNITS | D2039: Z08094 | E2039: MOBILE SERVICE UNIT 082303370 | F2039: MSU | G2039: =VLOOKUP(A2039,Sheet2!A:J,1,0) -> 90040Z08094 | H2039: =VLOOKUP(A2039,Sheet2!A:J,10,0) -> MOBILE SERVICE UNITS | I2039: =IF(F2039=H2039,TRUE,FALSE) -> FALSE
A2040: =B2040&D2040 -> 90041120359210 | B2040: 90041 | C2040: AED - SPARES | D2040: 120359210 | E2040: ARM ASSEMBLY SHORT | F2040: SPARES / ACCESSORIES | G2040: =VLOOKUP(A2040,Sheet2!A:J,1,0) -> #N/A | H2040: =VLOOKUP(A2040,Sheet2!A:J,6,0) -> #N/A
A2041: =B2041&D2041 -> 90041120354620 | B2041: 90041 | C2041: AED - SPARES | D2041: 120354620 | E2041: COLUMN FOLLOWER | F2041: SPARES / ACCESSORIES | G2041: =VLOOKUP(A2041,Sheet2!A:J,1,0) -> #N/A | H2041: =VLOOKUP(A2041,Sheet2!A:J,6,0) -> #N/A
A2042: =B2042&D2042 -> 90041120369630 | B2042: 90041 | C2042: AED - SPARES | D2042: 120369630 | E2042: SHORT ARM ASSY MASTER-1030MM | F2042: SPARES / ACCESSORIES | G2042: =VLOOKUP(A2042,Sheet2!A:J,1,0) -> #N/A | H2042: =VLOOKUP(A2042,Sheet2!A:J,6,0) -> #N/A
A2043: =B2043&D2043 -> 90041120354690 | B2043: 90041 | C2043: AED - SPARES | D2043: 120354690 | E2043: LOCKING ARRANGE.ASSY,ARM | F2043: SPARES / ACCESSORIES | G2043: =VLOOKUP(A2043,Sheet2!A:J,1,0) -> #N/A | H2043: =VLOOKUP(A2043,Sheet2!A:J,6,0) -> #N/A
A2044: =B2044&D2044 -> 90041120369640 | B2044: 90041 | C2044: AED - SPARES | D2044: 120369640 | E2044: SHORT ARM ASSY SLAVE-1030MM | F2044: SPARES / ACCESSORIES | G2044: =VLOOKUP(A2044,Sheet2!A:J,1,0) -> #N/A | H2044: =VLOOKUP(A2044,Sheet2!A:J,6,0) -> #N/A
A2045: =B2045&D2045 -> 9004116CGLO5931EL | B2045: 90041 | C2045: AED - SPARES | D2045: 16CGLO5931EL | E2045: TRADE MARK ELSEA F.TO59X31,5E0 | F2045: SPARES / ACCESSORIES | G2045: =VLOOKUP(A2045,Sheet2!A:J,1,0) -> #N/A | H2045: =VLOOKUP(A2045,Sheet2!A:J,6,0) -> #N/A
...

Sheet Sheet4
A1: ProductGrp
A2: AC CHARGING MACHINE
A3: ACW
A4: BODY SHOP & PAINT EQUIPMENTS - CRS
A5: BODY SHOP & PAINT EQUIPMENTS - OTHERS
A6: BODY SHOP & PAINT EQUIPMENTS - PANEL REPAIR
A7: BODY SHOP & PAINT EQUIPMENTS - PB
A8: BODY SHOP & PAINT EQUIPMENTS - WELDERS
A9: Consumables
A10: ETP
A11: FRT
A12: International Sales
... A35: WHEEL SERVICE EQUIPMENTS
